[
    {
        "all_awardings": [],
        "archived": false,
        "associated_award": null,
        "author": "WolfThawra",
        "author_created_utc": 1391804071,
        "author_flair_background_color": null,
        "author_flair_css_class": null,
        "author_flair_richtext": [],
        "author_flair_template_id": null,
        "author_flair_text": null,
        "author_flair_text_color": null,
        "author_flair_type": "text",
        "author_fullname": "t2_f63no",
        "author_patreon_flair": false,
        "author_premium": true,
        "body": "Aus leidvoller Erfahrung kann ich sagen, dass es zwei Probleme gibt: einmal Schimmel, wie du sagst. Da k\u00f6nnte so ein Luftentfeuchter durchaus helfen, wobei ich mich da mit Besorgungskosten oder Mietm\u00f6glichkeiten nicht auskenne. Theoretisch gibts so Dinger zum Austrocknen von Kellerr\u00e4umen nach \u00dcberschwemmungen, es m\u00fcsste also ein paar ungenutzte Exemplare geben, aber ob sie dir die einfach so ausleihen...\n\nZweitens kommt aber, je nach Kochstil, auch noch das Problem von Fett hinzu. Wir haben eine Weile lang in einer Wohnung gelebt, die keinen richtigen Dunstabzug hatte. Die obere H\u00e4lfte des Raums hat mit der Zeit eine ziemlich eklige Fettschicht angesammelt, es war einfach alles irgendwie schmierig. Wie genau das zustande kommt, weiss ich auch nicht genau - vielleicht werden kleine Fettpartikel in Dunst und Rauch mittransportiert und lagern sich dann ab? Jedenfalls langfristig nicht zu empfehlen. F\u00fcr wenige Monate geht's vielleicht noch OK, aber ich w\u00fcrde mich nicht wundern, wenn du hinterher die W\u00e4nde und oben an K\u00fcchenschr\u00e4nken etc. putzen musst.",
        "can_gild": true,
        "collapsed": false,
        "collapsed_because_crowd_control": null,
        "collapsed_reason": null,
        "collapsed_reason_code": null,
        "comment_type": null,
        "controversiality": 0,
        "created_utc": 1636969070,
        "distinguished": null,
        "edited": false,
        "gilded": 0,
        "gildings": {},
        "id": "hkpalwy",
        "is_submitter": false,
        "link_id": "t3_quclv3",
        "locked": false,
        "name": "t1_hkpalwy",
        "no_follow": false,
        "parent_id": "t3_quclv3",
        "permalink": "/r/wohnen/comments/quclv3/k\u00fcchenfenster_defekt_wie_l\u00fcften/hkpalwy/",
        "retrieved_on": 1646016261,
        "score": 5,
        "score_hidden": false,
        "send_replies": true,
        "stickied": false,
        "subreddit": "wohnen",
        "subreddit_id": "t5_kz98g",
        "subreddit_name_prefixed": "r/wohnen",
        "subreddit_type": "public",
        "top_awarded_type": null,
        "total_awards_received": 0,
        "treatment_tags": [],
        "unrepliable_reason": null,
        "responses": []
    },
    {
        "all_awardings": [],
        "archived": false,
        "associated_award": null,
        "author": "DR58_24",
        "author_created_utc": 1636966823,
        "author_flair_background_color": null,
        "author_flair_css_class": null,
        "author_flair_richtext": [],
        "author_flair_template_id": null,
        "author_flair_text": null,
        "author_flair_text_color": null,
        "author_flair_type": "text",
        "author_fullname": "t2_gkbwv431",
        "author_patreon_flair": false,
        "author_premium": false,
        "body": "Ja, das Problem mit dem Fett kennen wir gut, wir wohnen schon mehrere Jahre in der Wohnung. Da hilft auch ein ge\u00f6ffnetes Fenster wenig, das Zeug h\u00e4ngt einfach \u00fcberall.     \n\nIn der n\u00e4chsten Wohnung wird wohl eine Abzugshaube Pflicht, ist im Moment aber defintiv nicht m\u00f6glich. Die K\u00fcche ist einfach viel zu klein und direkt \u00fcber dem Herd sind H\u00e4ngeschr\u00e4nke angebracht, was absolut irrsinnig ist aber egal.     \n\nPrim\u00e4r geht es mir jetzt nur darum, das Risiko Schimmel zu minimieren und deshalb die Idee mit dem Entfeuchter. Ob das aber wirklich etwas bringt wei\u00df ich nicht. W\u00fcrde ich zur Not auch selbst anschaffen, falls ein \"kleines\" Ger\u00e4t ausreichend w\u00e4re. Sind scheinbar um die 100\u20ac beim Baumarkt erh\u00e4ltlich - aber ob das was taugt?",
        "can_gild": true,
        "collapsed": false,
        "collapsed_because_crowd_control": null,
        "collapsed_reason": null,
        "collapsed_reason_code": null,
        "comment_type": null,
        "controversiality": 0,
        "created_utc": 1636969477,
        "distinguished": null,
        "edited": false,
        "gilded": 0,
        "gildings": {},
        "id": "hkpb2sp",
        "is_submitter": true,
        "link_id": "t3_quclv3",
        "locked": false,
        "name": "t1_hkpb2sp",
        "no_follow": false,
        "parent_id": "t1_hkpalwy",
        "permalink": "/r/wohnen/comments/quclv3/k\u00fcchenfenster_defekt_wie_l\u00fcften/hkpb2sp/",
        "retrieved_on": 1646016234,
        "score": 2,
        "score_hidden": false,
        "send_replies": true,
        "stickied": false,
        "subreddit": "wohnen",
        "subreddit_id": "t5_kz98g",
        "subreddit_name_prefixed": "r/wohnen",
        "subreddit_type": "public",
        "top_awarded_type": null,
        "total_awards_received": 0,
        "treatment_tags": [],
        "unrepliable_reason": null,
        "responses": []
    },
    {
        "all_awardings": [],
        "archived": false,
        "associated_award": null,
        "author": "Goetheborg",
        "author_created_utc": 1636747194,
        "author_flair_background_color": null,
        "author_flair_css_class": null,
        "author_flair_richtext": [],
        "author_flair_template_id": null,
        "author_flair_text": null,
        "author_flair_text_color": null,
        "author_flair_type": "text",
        "author_fullname": "t2_ghc6x5fq",
        "author_patreon_flair": false,
        "author_premium": false,
        "body": "Luftentfeuchter sind laute Stromfresser. Den Stromverbrauch k\u00f6nnt ihr vielleicht noch verkraften wenn es nur um wenige Monate geht, aber gem\u00fctliches in der K\u00fcche sitzen, oder im Nebenraum, d\u00fcrfte damit fast unm\u00f6glich sein. Ich k\u00f6nnte mir vorstellen, dass es mit der Zeit an die Nerven geht.",
        "can_gild": true,
        "collapsed": false,
        "collapsed_because_crowd_control": null,
        "collapsed_reason": null,
        "collapsed_reason_code": null,
        "comment_type": null,
        "controversiality": 0,
        "created_utc": 1636974016,
        "distinguished": null,
        "edited": false,
        "gilded": 0,
        "gildings": {},
        "id": "hkpgdng",
        "is_submitter": false,
        "link_id": "t3_quclv3",
        "locked": false,
        "name": "t1_hkpgdng",
        "no_follow": true,
        "parent_id": "t3_quclv3",
        "permalink": "/r/wohnen/comments/quclv3/k\u00fcchenfenster_defekt_wie_l\u00fcften/hkpgdng/",
        "retrieved_on": 1646015902,
        "score": 2,
        "score_hidden": false,
        "send_replies": true,
        "stickied": false,
        "subreddit": "wohnen",
        "subreddit_id": "t5_kz98g",
        "subreddit_name_prefixed": "r/wohnen",
        "subreddit_type": "public",
        "top_awarded_type": null,
        "total_awards_received": 0,
        "treatment_tags": [],
        "unrepliable_reason": null,
        "responses": []
    },
    {
        "all_awardings": [],
        "archived": false,
        "associated_award": null,
        "author": "wilisi",
        "author_created_utc": 1546952289,
        "author_flair_background_color": null,
        "author_flair_css_class": null,
        "author_flair_richtext": [],
        "author_flair_template_id": null,
        "author_flair_text": null,
        "author_flair_text_color": null,
        "author_flair_type": "text",
        "author_fullname": "t2_2y8k4aji",
        "author_patreon_flair": false,
        "author_premium": false,
        "body": "Ich w\u00fcrde erstmal Hygrometer anschaffen um das im Blick zu behalten. Evtl reicht es ja schon, die T\u00fcr in einen gut bel\u00fcfteten Nebenraum (mit eigenem Hygrometer) offen zu lassen, oder gelegentlich einen Standventilator anzumachen.\n\nDu kannst auch an der Quelle ansetzen: eher backen, evtl. eher braten (oder auch nicht, das Fett-Problem wurde ja schon erw\u00e4hnt), Wasser nicht l\u00e4nger als n\u00f6tig sprudelnd aufkochen lassen, einen Schnellkochtopf nehmen und den Druck an einem Fenster ablassen, besonders \"nasse\" Gerichte bevorzugt an Tagen mit trockener Au\u00dfenluft kochen.",
        "can_gild": true,
        "collapsed": false,
        "collapsed_because_crowd_control": null,
        "collapsed_reason": null,
        "collapsed_reason_code": null,
        "comment_type": null,
        "controversiality": 0,
        "created_utc": 1636981813,
        "distinguished": null,
        "edited": false,
        "gilded": 0,
        "gildings": {},
        "id": "hkprrx2",
        "is_submitter": false,
        "link_id": "t3_quclv3",
        "locked": false,
        "name": "t1_hkprrx2",
        "no_follow": true,
        "parent_id": "t3_quclv3",
        "permalink": "/r/wohnen/comments/quclv3/k\u00fcchenfenster_defekt_wie_l\u00fcften/hkprrx2/",
        "retrieved_on": 1646015227,
        "score": 3,
        "score_hidden": false,
        "send_replies": true,
        "stickied": false,
        "subreddit": "wohnen",
        "subreddit_id": "t5_kz98g",
        "subreddit_name_prefixed": "r/wohnen",
        "subreddit_type": "public",
        "top_awarded_type": null,
        "total_awards_received": 0,
        "treatment_tags": [],
        "unrepliable_reason": null,
        "responses": []
    },
    {
        "all_awardings": [],
        "archived": false,
        "associated_award": null,
        "author": "Fleecimton",
        "author_created_utc": 1528286064,
        "author_flair_background_color": null,
        "author_flair_css_class": null,
        "author_flair_richtext": [],
        "author_flair_template_id": null,
        "author_flair_text": null,
        "author_flair_text_color": null,
        "author_flair_type": "text",
        "author_fullname": "t2_t0ukiu0",
        "author_patreon_flair": false,
        "author_premium": false,
        "body": "Dein Vermieter hat daf\u00fcr sorge zu tragen, dass du schnellstm\u00f6glich Ersatz bekommst. 1. Gibt es mehrere Anbieter von Fenstern und 2. Herrscht zwar Rohstoffmangel, aber das ist eher beim Holz der Fall.",
        "can_gild": true,
        "collapsed": false,
        "collapsed_because_crowd_control": null,
        "collapsed_reason": null,
        "collapsed_reason_code": null,
        "comment_type": null,
        "controversiality": 0,
        "created_utc": 1637327336,
        "distinguished": null,
        "edited": false,
        "gilded": 0,
        "gildings": {},
        "id": "hl90wt3",
        "is_submitter": false,
        "link_id": "t3_quclv3",
        "locked": false,
        "name": "t1_hl90wt3",
        "no_follow": true,
        "parent_id": "t3_quclv3",
        "permalink": "/r/wohnen/comments/quclv3/k\u00fcchenfenster_defekt_wie_l\u00fcften/hl90wt3/",
        "retrieved_on": 1645973942,
        "score": 1,
        "score_hidden": false,
        "send_replies": true,
        "stickied": false,
        "subreddit": "wohnen",
        "subreddit_id": "t5_kz98g",
        "subreddit_name_prefixed": "r/wohnen",
        "subreddit_type": "public",
        "top_awarded_type": null,
        "total_awards_received": 0,
        "treatment_tags": [],
        "unrepliable_reason": null,
        "responses": []
    }
]