[
    {
        "_meta": {
            "retrieved_2nd_on": 1702600768
        },
        "all_awardings": [],
        "approved_at_utc": null,
        "approved_by": null,
        "archived": false,
        "associated_award": null,
        "author": "MaikiMaxim",
        "author_flair_background_color": null,
        "author_flair_css_class": null,
        "author_flair_richtext": [],
        "author_flair_template_id": null,
        "author_flair_text": null,
        "author_flair_text_color": null,
        "author_flair_type": "text",
        "author_fullname": "t2_naob6ct",
        "author_is_blocked": false,
        "author_patreon_flair": false,
        "author_premium": false,
        "awarders": [],
        "banned_at_utc": null,
        "banned_by": null,
        "body": "Wir haben grade frisch mit DayZ auf nem eigenen Server angefangen. \n\nMarauders spielen wir auch seit neuestem. Unser Hauptgame ist allerdings Counter Strike. \nMelde dich gern bei Interesse! :)",
        "can_gild": false,
        "can_mod_post": false,
        "collapsed": false,
        "collapsed_because_crowd_control": null,
        "collapsed_reason": null,
        "collapsed_reason_code": null,
        "comment_type": null,
        "controversiality": 0,
        "created": 1702471162.0,
        "created_utc": 1702471162.0,
        "distinguished": null,
        "downs": 0,
        "edited": false,
        "gilded": 0,
        "gildings": {},
        "id": "kd67ofi",
        "is_submitter": false,
        "likes": null,
        "link_id": "t3_18hfmoq",
        "locked": false,
        "mod_note": null,
        "mod_reason_by": null,
        "mod_reason_title": null,
        "mod_reports": [],
        "name": "t1_kd67ofi",
        "no_follow": true,
        "num_reports": 0,
        "parent_id": "t3_18hfmoq",
        "permalink": "/r/zocken/comments/18hfmoq/suche_wen_zum_zocken_1_2_die_woche_abends_ca_nach/kd67ofi/",
        "removal_reason": null,
        "replies": "",
        "report_reasons": [],
        "retrieved_on": 1702471175,
        "saved": false,
        "score": 2,
        "score_hidden": false,
        "send_replies": true,
        "stickied": false,
        "subreddit": "zocken",
        "subreddit_id": "t5_2vz1s",
        "subreddit_name_prefixed": "r/zocken",
        "subreddit_type": "public",
        "top_awarded_type": null,
        "total_awards_received": 0,
        "treatment_tags": [],
        "unrepliable_reason": null,
        "updated_on": 1702471192,
        "ups": 2,
        "user_reports": [],
        "responses": []
    },
    {
        "_meta": {
            "retrieved_2nd_on": 1702600987
        },
        "all_awardings": [],
        "approved_at_utc": null,
        "approved_by": null,
        "archived": false,
        "associated_award": null,
        "author": "Pale-Grapefruit-7802",
        "author_flair_background_color": null,
        "author_flair_css_class": null,
        "author_flair_richtext": [],
        "author_flair_template_id": null,
        "author_flair_text": null,
        "author_flair_text_color": null,
        "author_flair_type": "text",
        "author_fullname": "t2_nxy4dsjc",
        "author_is_blocked": false,
        "author_patreon_flair": false,
        "author_premium": false,
        "awarders": [],
        "banned_at_utc": null,
        "banned_by": null,
        "body": "Das ist mir alles zu viel shooter. Aber danke",
        "can_gild": false,
        "can_mod_post": false,
        "collapsed": false,
        "collapsed_because_crowd_control": null,
        "collapsed_reason": null,
        "collapsed_reason_code": null,
        "comment_type": null,
        "controversiality": 0,
        "created": 1702471376.0,
        "created_utc": 1702471376.0,
        "distinguished": null,
        "downs": 0,
        "edited": false,
        "gilded": 0,
        "gildings": {},
        "id": "kd682h0",
        "is_submitter": true,
        "likes": null,
        "link_id": "t3_18hfmoq",
        "locked": false,
        "mod_note": null,
        "mod_reason_by": null,
        "mod_reason_title": null,
        "mod_reports": [],
        "name": "t1_kd682h0",
        "no_follow": true,
        "num_reports": 0,
        "parent_id": "t1_kd67ofi",
        "permalink": "/r/zocken/comments/18hfmoq/suche_wen_zum_zocken_1_2_die_woche_abends_ca_nach/kd682h0/",
        "removal_reason": null,
        "replies": "",
        "report_reasons": [],
        "retrieved_on": 1702471391,
        "saved": false,
        "score": 1,
        "score_hidden": false,
        "send_replies": true,
        "stickied": false,
        "subreddit": "zocken",
        "subreddit_id": "t5_2vz1s",
        "subreddit_name_prefixed": "r/zocken",
        "subreddit_type": "public",
        "top_awarded_type": null,
        "total_awards_received": 0,
        "treatment_tags": [],
        "unrepliable_reason": null,
        "updated_on": 1702471408,
        "ups": 1,
        "user_reports": [],
        "responses": []
    },
    {
        "_meta": {
            "is_edited": true,
            "retrieved_2nd_on": 1702601434
        },
        "all_awardings": [],
        "approved_at_utc": null,
        "approved_by": null,
        "archived": false,
        "associated_award": null,
        "author": "Death_IP",
        "author_flair_background_color": null,
        "author_flair_css_class": null,
        "author_flair_richtext": [],
        "author_flair_template_id": null,
        "author_flair_text": null,
        "author_flair_text_color": null,
        "author_flair_type": "text",
        "author_fullname": "t2_3b0hcsty",
        "author_is_blocked": false,
        "author_patreon_flair": false,
        "author_premium": false,
        "awarders": [],
        "banned_at_utc": null,
        "banned_by": null,
        "body": "MMORPGs 1-3h 2x die Woche? Wird wohl eine Lebensaufgabe.",
        "can_gild": false,
        "can_mod_post": false,
        "collapsed": false,
        "collapsed_because_crowd_control": null,
        "collapsed_reason": null,
        "collapsed_reason_code": null,
        "comment_type": null,
        "controversiality": 0,
        "created": 1702471827.0,
        "created_utc": 1702471827.0,
        "distinguished": null,
        "downs": 0,
        "edited": false,
        "gilded": 0,
        "gildings": {},
        "id": "kd68wn6",
        "is_submitter": false,
        "likes": null,
        "link_id": "t3_18hfmoq",
        "locked": false,
        "mod_note": null,
        "mod_reason_by": null,
        "mod_reason_title": null,
        "mod_reports": [],
        "name": "t1_kd68wn6",
        "no_follow": true,
        "num_reports": 0,
        "parent_id": "t3_18hfmoq",
        "permalink": "/r/zocken/comments/18hfmoq/suche_wen_zum_zocken_1_2_die_woche_abends_ca_nach/kd68wn6/",
        "removal_reason": null,
        "replies": "",
        "report_reasons": [],
        "retrieved_on": 1702471842,
        "saved": false,
        "score": -12,
        "score_hidden": false,
        "send_replies": true,
        "stickied": false,
        "subreddit": "zocken",
        "subreddit_id": "t5_2vz1s",
        "subreddit_name_prefixed": "r/zocken",
        "subreddit_type": "public",
        "top_awarded_type": null,
        "total_awards_received": 0,
        "treatment_tags": [],
        "unrepliable_reason": null,
        "updated_on": 1702471859,
        "ups": -12,
        "user_reports": [],
        "responses": []
    },
    {
        "_meta": {
            "retrieved_2nd_on": 1702601856
        },
        "all_awardings": [],
        "approved_at_utc": null,
        "approved_by": null,
        "archived": false,
        "associated_award": null,
        "author": "tobeymaguirefan2",
        "author_flair_background_color": null,
        "author_flair_css_class": null,
        "author_flair_richtext": [],
        "author_flair_template_id": null,
        "author_flair_text": null,
        "author_flair_text_color": null,
        "author_flair_type": "text",
        "author_fullname": "t2_o03s2dcuk",
        "author_is_blocked": false,
        "author_patreon_flair": false,
        "author_premium": false,
        "awarders": [],
        "banned_at_utc": null,
        "banned_by": null,
        "body": "Such dir in Guild Wars 2 eine Feierabend Gilde, w\u00fcrde perfekt passen ^^ gibt viele davon",
        "can_gild": false,
        "can_mod_post": false,
        "collapsed": false,
        "collapsed_because_crowd_control": null,
        "collapsed_reason": null,
        "collapsed_reason_code": null,
        "comment_type": null,
        "controversiality": 0,
        "created": 1702472245.0,
        "created_utc": 1702472245.0,
        "distinguished": null,
        "downs": 0,
        "edited": false,
        "gilded": 0,
        "gildings": {},
        "id": "kd69pbh",
        "is_submitter": false,
        "likes": null,
        "link_id": "t3_18hfmoq",
        "locked": false,
        "mod_note": null,
        "mod_reason_by": null,
        "mod_reason_title": null,
        "mod_reports": [],
        "name": "t1_kd69pbh",
        "no_follow": false,
        "num_reports": 0,
        "parent_id": "t3_18hfmoq",
        "permalink": "/r/zocken/comments/18hfmoq/suche_wen_zum_zocken_1_2_die_woche_abends_ca_nach/kd69pbh/",
        "removal_reason": null,
        "replies": "",
        "report_reasons": [],
        "retrieved_on": 1702472261,
        "saved": false,
        "score": 1,
        "score_hidden": false,
        "send_replies": true,
        "stickied": false,
        "subreddit": "zocken",
        "subreddit_id": "t5_2vz1s",
        "subreddit_name_prefixed": "r/zocken",
        "subreddit_type": "public",
        "top_awarded_type": null,
        "total_awards_received": 0,
        "treatment_tags": [],
        "unrepliable_reason": null,
        "updated_on": 1702472275,
        "ups": 1,
        "user_reports": [],
        "responses": []
    },
    {
        "_meta": {
            "retrieved_2nd_on": 1702602844
        },
        "all_awardings": [],
        "approved_at_utc": null,
        "approved_by": null,
        "archived": false,
        "associated_award": null,
        "author": "neunzehnhundert",
        "author_flair_background_color": null,
        "author_flair_css_class": null,
        "author_flair_richtext": [],
        "author_flair_template_id": null,
        "author_flair_text": null,
        "author_flair_text_color": null,
        "author_flair_type": "text",
        "author_fullname": "t2_iyhyt",
        "author_is_blocked": false,
        "author_patreon_flair": false,
        "author_premium": false,
        "awarders": [],
        "banned_at_utc": null,
        "banned_by": null,
        "body": "Quatsch. Spiele MMOs seit Jahren nur noch so. Klar spiel ich nicht mehr ganz oben mit aber Raiden oder im Falle von WoW M+ funktioniert auch casual sehr gut.",
        "can_gild": false,
        "can_mod_post": false,
        "collapsed": false,
        "collapsed_because_crowd_control": null,
        "collapsed_reason": null,
        "collapsed_reason_code": null,
        "comment_type": null,
        "controversiality": 0,
        "created": 1702473232.0,
        "created_utc": 1702473232.0,
        "distinguished": null,
        "downs": 0,
        "edited": false,
        "gilded": 0,
        "gildings": {},
        "id": "kd6bmj3",
        "is_submitter": false,
        "likes": null,
        "link_id": "t3_18hfmoq",
        "locked": false,
        "mod_note": null,
        "mod_reason_by": null,
        "mod_reason_title": null,
        "mod_reports": [],
        "name": "t1_kd6bmj3",
        "no_follow": true,
        "num_reports": 0,
        "parent_id": "t1_kd68wn6",
        "permalink": "/r/zocken/comments/18hfmoq/suche_wen_zum_zocken_1_2_die_woche_abends_ca_nach/kd6bmj3/",
        "removal_reason": null,
        "replies": "",
        "report_reasons": [],
        "retrieved_on": 1702473250,
        "saved": false,
        "score": 9,
        "score_hidden": false,
        "send_replies": true,
        "stickied": false,
        "subreddit": "zocken",
        "subreddit_id": "t5_2vz1s",
        "subreddit_name_prefixed": "r/zocken",
        "subreddit_type": "public",
        "top_awarded_type": null,
        "total_awards_received": 0,
        "treatment_tags": [],
        "unrepliable_reason": null,
        "updated_on": 1702473264,
        "ups": 9,
        "user_reports": [],
        "responses": []
    },
    {
        "_meta": {
            "retrieved_2nd_on": 1702603515
        },
        "all_awardings": [],
        "approved_at_utc": null,
        "approved_by": null,
        "archived": false,
        "associated_award": null,
        "author": "Ieaki-98",
        "author_flair_background_color": null,
        "author_flair_css_class": null,
        "author_flair_richtext": [],
        "author_flair_template_id": null,
        "author_flair_text": null,
        "author_flair_text_color": null,
        "author_flair_type": "text",
        "author_fullname": "t2_p84wqw17w",
        "author_is_blocked": false,
        "author_patreon_flair": false,
        "author_premium": false,
        "awarders": [],
        "banned_at_utc": null,
        "banned_by": null,
        "body": "Auf welchem Server bist du bei FF14? \nIch bin bei Licht (Light) und am Ende von Endwalker (ohne Update-Main-Scenario)",
        "can_gild": false,
        "can_mod_post": false,
        "collapsed": false,
        "collapsed_because_crowd_control": null,
        "collapsed_reason": null,
        "collapsed_reason_code": null,
        "comment_type": null,
        "controversiality": 0,
        "created": 1702473905.0,
        "created_utc": 1702473905.0,
        "distinguished": null,
        "downs": 0,
        "edited": false,
        "gilded": 0,
        "gildings": {},
        "id": "kd6cylj",
        "is_submitter": false,
        "likes": null,
        "link_id": "t3_18hfmoq",
        "locked": false,
        "mod_note": null,
        "mod_reason_by": null,
        "mod_reason_title": null,
        "mod_reports": [],
        "name": "t1_kd6cylj",
        "no_follow": true,
        "num_reports": 0,
        "parent_id": "t3_18hfmoq",
        "permalink": "/r/zocken/comments/18hfmoq/suche_wen_zum_zocken_1_2_die_woche_abends_ca_nach/kd6cylj/",
        "removal_reason": null,
        "replies": "",
        "report_reasons": [],
        "retrieved_on": 1702473921,
        "saved": false,
        "score": 4,
        "score_hidden": false,
        "send_replies": true,
        "stickied": false,
        "subreddit": "zocken",
        "subreddit_id": "t5_2vz1s",
        "subreddit_name_prefixed": "r/zocken",
        "subreddit_type": "public",
        "top_awarded_type": null,
        "total_awards_received": 0,
        "treatment_tags": [],
        "unrepliable_reason": null,
        "updated_on": 1702473935,
        "ups": 4,
        "user_reports": [],
        "responses": []
    },
    {
        "_meta": {
            "is_edited": true,
            "retrieved_2nd_on": 1702603562
        },
        "all_awardings": [],
        "approved_at_utc": null,
        "approved_by": null,
        "archived": false,
        "associated_award": null,
        "author": "L1ghtbird",
        "author_flair_background_color": null,
        "author_flair_css_class": null,
        "author_flair_richtext": [],
        "author_flair_template_id": null,
        "author_flair_text": null,
        "author_flair_text_color": null,
        "author_flair_type": "text",
        "author_fullname": "t2_ucri9ub2",
        "author_is_blocked": false,
        "author_patreon_flair": false,
        "author_premium": false,
        "awarders": [],
        "banned_at_utc": null,
        "banned_by": null,
        "body": "Spiel mal Guild Wars 2, da kannst auch 2, 3 Jahre pausieren und dein Gear ist immernoch stark. Trotzdem gibt's genug zu tun, um dich auch als dauerzocker bei Laune zu halten",
        "can_gild": false,
        "can_mod_post": false,
        "collapsed": false,
        "collapsed_because_crowd_control": null,
        "collapsed_reason": null,
        "collapsed_reason_code": null,
        "comment_type": null,
        "controversiality": 0,
        "created": 1702473952.0,
        "created_utc": 1702473952.0,
        "distinguished": null,
        "downs": 0,
        "edited": false,
        "gilded": 0,
        "gildings": {},
        "id": "kd6d231",
        "is_submitter": false,
        "likes": null,
        "link_id": "t3_18hfmoq",
        "locked": false,
        "mod_note": null,
        "mod_reason_by": null,
        "mod_reason_title": null,
        "mod_reports": [],
        "name": "t1_kd6d231",
        "no_follow": true,
        "num_reports": 0,
        "parent_id": "t1_kd68wn6",
        "permalink": "/r/zocken/comments/18hfmoq/suche_wen_zum_zocken_1_2_die_woche_abends_ca_nach/kd6d231/",
        "removal_reason": null,
        "replies": "",
        "report_reasons": [],
        "retrieved_on": 1702473965,
        "saved": false,
        "score": 3,
        "score_hidden": false,
        "send_replies": true,
        "stickied": false,
        "subreddit": "zocken",
        "subreddit_id": "t5_2vz1s",
        "subreddit_name_prefixed": "r/zocken",
        "subreddit_type": "public",
        "top_awarded_type": null,
        "total_awards_received": 0,
        "treatment_tags": [],
        "unrepliable_reason": null,
        "updated_on": 1702473982,
        "ups": 3,
        "user_reports": [],
        "responses": []
    },
    {
        "_meta": {
            "retrieved_2nd_on": 1702607501
        },
        "all_awardings": [],
        "approved_at_utc": null,
        "approved_by": null,
        "archived": false,
        "associated_award": null,
        "author": "Hoard4",
        "author_flair_background_color": null,
        "author_flair_css_class": null,
        "author_flair_richtext": [],
        "author_flair_template_id": null,
        "author_flair_text": null,
        "author_flair_text_color": null,
        "author_flair_type": "text",
        "author_fullname": "t2_bsdwgg7",
        "author_is_blocked": false,
        "author_patreon_flair": false,
        "author_premium": false,
        "awarders": [],
        "banned_at_utc": null,
        "banned_by": null,
        "body": "Gr\u00fc\u00dfe,\n\nBei deinen Builder/Survival spielen w\u00e4re ich dabei. \n\nSatisfactory hab ich bis zu letzten Phase gespielt aber dann ne Pause eingelegt. Wollte jetzt nach Update 8 mal wieder reinschauen. \n\nMinecraft wollte ich nach den ganzen Updates auch immer mal wieder spielen aber alleine verliere ich immer schnell die Motivation. \n\nFactorio besitze ich zwar noch nicht, hab aber geh\u00f6rt das es super sein soll. Und da ich satisfactory einfach gro\u00dfartig finde, ist Factorio definitiv auch auf meiner Liste :D",
        "can_gild": false,
        "can_mod_post": false,
        "collapsed": false,
        "collapsed_because_crowd_control": null,
        "collapsed_reason": null,
        "collapsed_reason_code": null,
        "comment_type": null,
        "controversiality": 0,
        "created": 1702477892.0,
        "created_utc": 1702477892.0,
        "distinguished": null,
        "downs": 0,
        "edited": false,
        "gilded": 0,
        "gildings": {},
        "id": "kd6lobz",
        "is_submitter": false,
        "likes": null,
        "link_id": "t3_18hfmoq",
        "locked": false,
        "mod_note": null,
        "mod_reason_by": null,
        "mod_reason_title": null,
        "mod_reports": [],
        "name": "t1_kd6lobz",
        "no_follow": true,
        "num_reports": 0,
        "parent_id": "t3_18hfmoq",
        "permalink": "/r/zocken/comments/18hfmoq/suche_wen_zum_zocken_1_2_die_woche_abends_ca_nach/kd6lobz/",
        "removal_reason": null,
        "replies": "",
        "report_reasons": [],
        "retrieved_on": 1702477908,
        "saved": false,
        "score": 1,
        "score_hidden": false,
        "send_replies": true,
        "stickied": false,
        "subreddit": "zocken",
        "subreddit_id": "t5_2vz1s",
        "subreddit_name_prefixed": "r/zocken",
        "subreddit_type": "public",
        "top_awarded_type": null,
        "total_awards_received": 0,
        "treatment_tags": [],
        "unrepliable_reason": null,
        "updated_on": 1702477924,
        "ups": 1,
        "user_reports": [],
        "responses": []
    },
    {
        "_meta": {
            "retrieved_2nd_on": 1702607658
        },
        "all_awardings": [],
        "approved_at_utc": null,
        "approved_by": null,
        "archived": false,
        "associated_award": null,
        "author": "derBruzzler",
        "author_flair_background_color": null,
        "author_flair_css_class": null,
        "author_flair_richtext": [],
        "author_flair_template_id": null,
        "author_flair_text": null,
        "author_flair_text_color": null,
        "author_flair_type": "text",
        "author_fullname": "t2_6bttbjp1",
        "author_is_blocked": false,
        "author_patreon_flair": false,
        "author_premium": false,
        "awarders": [],
        "banned_at_utc": null,
        "banned_by": null,
        "body": "welches CS spielt ihr?",
        "can_gild": false,
        "can_mod_post": false,
        "collapsed": false,
        "collapsed_because_crowd_control": null,
        "collapsed_reason": null,
        "collapsed_reason_code": null,
        "comment_type": null,
        "controversiality": 0,
        "created": 1702478051.0,
        "created_utc": 1702478051.0,
        "distinguished": null,
        "downs": 0,
        "edited": false,
        "gilded": 0,
        "gildings": {},
        "id": "kd6m1rj",
        "is_submitter": false,
        "likes": null,
        "link_id": "t3_18hfmoq",
        "locked": false,
        "mod_note": null,
        "mod_reason_by": null,
        "mod_reason_title": null,
        "mod_reports": [],
        "name": "t1_kd6m1rj",
        "no_follow": true,
        "num_reports": 0,
        "parent_id": "t1_kd67ofi",
        "permalink": "/r/zocken/comments/18hfmoq/suche_wen_zum_zocken_1_2_die_woche_abends_ca_nach/kd6m1rj/",
        "removal_reason": null,
        "replies": "",
        "report_reasons": [],
        "retrieved_on": 1702478065,
        "saved": false,
        "score": -1,
        "score_hidden": false,
        "send_replies": true,
        "stickied": false,
        "subreddit": "zocken",
        "subreddit_id": "t5_2vz1s",
        "subreddit_name_prefixed": "r/zocken",
        "subreddit_type": "public",
        "top_awarded_type": null,
        "total_awards_received": 0,
        "treatment_tags": [],
        "unrepliable_reason": null,
        "updated_on": 1702478082,
        "ups": -1,
        "user_reports": [],
        "responses": []
    },
    {
        "_meta": {
            "retrieved_2nd_on": 1702607693
        },
        "all_awardings": [],
        "approved_at_utc": null,
        "approved_by": null,
        "archived": false,
        "associated_award": null,
        "author": "MaikiMaxim",
        "author_flair_background_color": null,
        "author_flair_css_class": null,
        "author_flair_richtext": [],
        "author_flair_template_id": null,
        "author_flair_text": null,
        "author_flair_text_color": null,
        "author_flair_type": "text",
        "author_fullname": "t2_naob6ct",
        "author_is_blocked": false,
        "author_patreon_flair": false,
        "author_premium": false,
        "awarders": [],
        "banned_at_utc": null,
        "banned_by": null,
        "body": "Das neue",
        "can_gild": false,
        "can_mod_post": false,
        "collapsed": false,
        "collapsed_because_crowd_control": null,
        "collapsed_reason": null,
        "collapsed_reason_code": null,
        "comment_type": null,
        "controversiality": 0,
        "created": 1702478081.0,
        "created_utc": 1702478081.0,
        "distinguished": null,
        "downs": 0,
        "edited": false,
        "gilded": 0,
        "gildings": {},
        "id": "kd6m4bo",
        "is_submitter": false,
        "likes": null,
        "link_id": "t3_18hfmoq",
        "locked": false,
        "mod_note": null,
        "mod_reason_by": null,
        "mod_reason_title": null,
        "mod_reports": [],
        "name": "t1_kd6m4bo",
        "no_follow": true,
        "num_reports": 0,
        "parent_id": "t1_kd6m1rj",
        "permalink": "/r/zocken/comments/18hfmoq/suche_wen_zum_zocken_1_2_die_woche_abends_ca_nach/kd6m4bo/",
        "removal_reason": null,
        "replies": "",
        "report_reasons": [],
        "retrieved_on": 1702478096,
        "saved": false,
        "score": 1,
        "score_hidden": false,
        "send_replies": true,
        "stickied": false,
        "subreddit": "zocken",
        "subreddit_id": "t5_2vz1s",
        "subreddit_name_prefixed": "r/zocken",
        "subreddit_type": "public",
        "top_awarded_type": null,
        "total_awards_received": 0,
        "treatment_tags": [],
        "unrepliable_reason": null,
        "updated_on": 1702478111,
        "ups": 1,
        "user_reports": [],
        "responses": []
    },
    {
        "_meta": {
            "retrieved_2nd_on": 1702610697
        },
        "all_awardings": [],
        "approved_at_utc": null,
        "approved_by": null,
        "archived": false,
        "associated_award": null,
        "author": "Distinct-Job-7984",
        "author_flair_background_color": null,
        "author_flair_css_class": null,
        "author_flair_richtext": [],
        "author_flair_template_id": null,
        "author_flair_text": null,
        "author_flair_text_color": null,
        "author_flair_type": "text",
        "author_fullname": "t2_254xug4i",
        "author_is_blocked": false,
        "author_patreon_flair": false,
        "author_premium": false,
        "awarders": [],
        "banned_at_utc": null,
        "banned_by": null,
        "body": "Bin grad bei factorio in der seablock mod unterwegs krasse Rezepte da w\u00e4re hilfe gern gesehen...",
        "can_gild": false,
        "can_mod_post": false,
        "collapsed": false,
        "collapsed_because_crowd_control": null,
        "collapsed_reason": null,
        "collapsed_reason_code": null,
        "comment_type": null,
        "controversiality": 0,
        "created": 1702481090.0,
        "created_utc": 1702481090.0,
        "distinguished": null,
        "downs": 0,
        "edited": false,
        "gilded": 0,
        "gildings": {},
        "id": "kd6ths1",
        "is_submitter": false,
        "likes": null,
        "link_id": "t3_18hfmoq",
        "locked": false,
        "mod_note": null,
        "mod_reason_by": null,
        "mod_reason_title": null,
        "mod_reports": [],
        "name": "t1_kd6ths1",
        "no_follow": true,
        "num_reports": 0,
        "parent_id": "t3_18hfmoq",
        "permalink": "/r/zocken/comments/18hfmoq/suche_wen_zum_zocken_1_2_die_woche_abends_ca_nach/kd6ths1/",
        "removal_reason": null,
        "replies": "",
        "report_reasons": [],
        "retrieved_on": 1702481108,
        "saved": false,
        "score": 2,
        "score_hidden": false,
        "send_replies": true,
        "stickied": false,
        "subreddit": "zocken",
        "subreddit_id": "t5_2vz1s",
        "subreddit_name_prefixed": "r/zocken",
        "subreddit_type": "public",
        "top_awarded_type": null,
        "total_awards_received": 0,
        "treatment_tags": [],
        "unrepliable_reason": null,
        "updated_on": 1702481121,
        "ups": 2,
        "user_reports": [],
        "responses": []
    },
    {
        "_meta": {
            "retrieved_2nd_on": 1702611086
        },
        "all_awardings": [],
        "approved_at_utc": null,
        "approved_by": null,
        "archived": false,
        "associated_award": null,
        "author": "Casualnoob666",
        "author_flair_background_color": null,
        "author_flair_css_class": null,
        "author_flair_richtext": [],
        "author_flair_template_id": null,
        "author_flair_text": null,
        "author_flair_text_color": null,
        "author_flair_type": "text",
        "author_fullname": "t2_2227hlbf",
        "author_is_blocked": false,
        "author_patreon_flair": false,
        "author_premium": false,
        "awarders": [],
        "banned_at_utc": null,
        "banned_by": null,
        "body": "Ich suche grad jemanden ungef\u00e4hr f\u00fcr den gleichen Zeitraum. F\u00fcr medieval dinasty. Survival, Aufbau und rpg Elemente.",
        "can_gild": false,
        "can_mod_post": false,
        "collapsed": false,
        "collapsed_because_crowd_control": null,
        "collapsed_reason": null,
        "collapsed_reason_code": null,
        "comment_type": null,
        "controversiality": 0,
        "created": 1702481476.0,
        "created_utc": 1702481476.0,
        "distinguished": null,
        "downs": 0,
        "edited": false,
        "gilded": 0,
        "gildings": {},
        "id": "kd6uh7h",
        "is_submitter": false,
        "likes": null,
        "link_id": "t3_18hfmoq",
        "locked": false,
        "mod_note": null,
        "mod_reason_by": null,
        "mod_reason_title": null,
        "mod_reports": [],
        "name": "t1_kd6uh7h",
        "no_follow": true,
        "num_reports": 0,
        "parent_id": "t3_18hfmoq",
        "permalink": "/r/zocken/comments/18hfmoq/suche_wen_zum_zocken_1_2_die_woche_abends_ca_nach/kd6uh7h/",
        "removal_reason": null,
        "replies": "",
        "report_reasons": [],
        "retrieved_on": 1702481504,
        "saved": false,
        "score": 1,
        "score_hidden": false,
        "send_replies": true,
        "stickied": false,
        "subreddit": "zocken",
        "subreddit_id": "t5_2vz1s",
        "subreddit_name_prefixed": "r/zocken",
        "subreddit_type": "public",
        "top_awarded_type": null,
        "total_awards_received": 0,
        "treatment_tags": [],
        "unrepliable_reason": null,
        "updated_on": 1702481507,
        "ups": 1,
        "user_reports": [],
        "responses": []
    },
    {
        "_meta": {
            "retrieved_2nd_on": 1702612110
        },
        "all_awardings": [],
        "approved_at_utc": null,
        "approved_by": null,
        "archived": false,
        "associated_award": null,
        "author": "IxdrowZeexI",
        "author_flair_background_color": null,
        "author_flair_css_class": null,
        "author_flair_richtext": [],
        "author_flair_template_id": null,
        "author_flair_text": null,
        "author_flair_text_color": null,
        "author_flair_type": "text",
        "author_fullname": "t2_ekysb",
        "author_is_blocked": false,
        "author_patreon_flair": false,
        "author_premium": false,
        "awarders": [],
        "banned_at_utc": null,
        "banned_by": null,
        "body": "Bin zwar nicht OP, aber h\u00e4tte auch Interesse bei DayZ zu joinen. Vorausgesetzt ihr spielt 1PP vanilla server",
        "can_gild": false,
        "can_mod_post": false,
        "collapsed": false,
        "collapsed_because_crowd_control": null,
        "collapsed_reason": null,
        "collapsed_reason_code": null,
        "comment_type": null,
        "controversiality": 0,
        "created": 1702482502.0,
        "created_utc": 1702482502.0,
        "distinguished": null,
        "downs": 0,
        "edited": false,
        "gilded": 0,
        "gildings": {},
        "id": "kd6x4ar",
        "is_submitter": false,
        "likes": null,
        "link_id": "t3_18hfmoq",
        "locked": false,
        "mod_note": null,
        "mod_reason_by": null,
        "mod_reason_title": null,
        "mod_reports": [],
        "name": "t1_kd6x4ar",
        "no_follow": true,
        "num_reports": 0,
        "parent_id": "t1_kd67ofi",
        "permalink": "/r/zocken/comments/18hfmoq/suche_wen_zum_zocken_1_2_die_woche_abends_ca_nach/kd6x4ar/",
        "removal_reason": null,
        "replies": "",
        "report_reasons": [],
        "retrieved_on": 1702482518,
        "saved": false,
        "score": -2,
        "score_hidden": false,
        "send_replies": true,
        "stickied": false,
        "subreddit": "zocken",
        "subreddit_id": "t5_2vz1s",
        "subreddit_name_prefixed": "r/zocken",
        "subreddit_type": "public",
        "top_awarded_type": null,
        "total_awards_received": 0,
        "treatment_tags": [],
        "unrepliable_reason": null,
        "updated_on": 1702482533,
        "ups": -2,
        "user_reports": [],
        "responses": []
    },
    {
        "_meta": {
            "retrieved_2nd_on": 1702612194
        },
        "all_awardings": [],
        "approved_at_utc": null,
        "approved_by": null,
        "archived": false,
        "associated_award": null,
        "author": "MaikiMaxim",
        "author_flair_background_color": null,
        "author_flair_css_class": null,
        "author_flair_richtext": [],
        "author_flair_template_id": null,
        "author_flair_text": null,
        "author_flair_text_color": null,
        "author_flair_type": "text",
        "author_fullname": "t2_naob6ct",
        "author_is_blocked": false,
        "author_patreon_flair": false,
        "author_premium": false,
        "awarders": [],
        "banned_at_utc": null,
        "banned_by": null,
        "body": "When das hei\u00dft first Person only, dann nein. Ein paar kleine mods wie zum\nBeispiel ne map",
        "can_gild": false,
        "can_mod_post": false,
        "collapsed": false,
        "collapsed_because_crowd_control": null,
        "collapsed_reason": null,
        "collapsed_reason_code": null,
        "comment_type": null,
        "controversiality": 0,
        "created": 1702482587.0,
        "created_utc": 1702482587.0,
        "distinguished": null,
        "downs": 0,
        "edited": false,
        "gilded": 0,
        "gildings": {},
        "id": "kd6xcde",
        "is_submitter": false,
        "likes": null,
        "link_id": "t3_18hfmoq",
        "locked": false,
        "mod_note": null,
        "mod_reason_by": null,
        "mod_reason_title": null,
        "mod_reports": [],
        "name": "t1_kd6xcde",
        "no_follow": true,
        "num_reports": 0,
        "parent_id": "t1_kd6x4ar",
        "permalink": "/r/zocken/comments/18hfmoq/suche_wen_zum_zocken_1_2_die_woche_abends_ca_nach/kd6xcde/",
        "removal_reason": null,
        "replies": "",
        "report_reasons": [],
        "retrieved_on": 1702482604,
        "saved": false,
        "score": 1,
        "score_hidden": false,
        "send_replies": true,
        "stickied": false,
        "subreddit": "zocken",
        "subreddit_id": "t5_2vz1s",
        "subreddit_name_prefixed": "r/zocken",
        "subreddit_type": "public",
        "top_awarded_type": null,
        "total_awards_received": 0,
        "treatment_tags": [],
        "unrepliable_reason": null,
        "updated_on": 1702482618,
        "ups": 1,
        "user_reports": [],
        "responses": []
    },
    {
        "_meta": {
            "retrieved_2nd_on": 1702612669
        },
        "all_awardings": [],
        "approved_at_utc": null,
        "approved_by": null,
        "archived": false,
        "associated_award": null,
        "author": "OkCare1776",
        "author_flair_background_color": null,
        "author_flair_css_class": null,
        "author_flair_richtext": [],
        "author_flair_template_id": null,
        "author_flair_text": null,
        "author_flair_text_color": null,
        "author_flair_type": "text",
        "author_fullname": "t2_479rm5eh",
        "author_is_blocked": false,
        "author_patreon_flair": false,
        "author_premium": false,
        "awarders": [],
        "banned_at_utc": null,
        "banned_by": null,
        "body": "Mit dem Serverhopping ist es ja zum Gl\u00fcck egal auf welchen Data center man ist. Das sollte kein Problem darstellen",
        "can_gild": false,
        "can_mod_post": false,
        "collapsed": false,
        "collapsed_because_crowd_control": null,
        "collapsed_reason": null,
        "collapsed_reason_code": null,
        "comment_type": null,
        "controversiality": 0,
        "created": 1702483060.0,
        "created_utc": 1702483060.0,
        "distinguished": null,
        "downs": 0,
        "edited": false,
        "gilded": 0,
        "gildings": {},
        "id": "kd6yl7x",
        "is_submitter": false,
        "likes": null,
        "link_id": "t3_18hfmoq",
        "locked": false,
        "mod_note": null,
        "mod_reason_by": null,
        "mod_reason_title": null,
        "mod_reports": [],
        "name": "t1_kd6yl7x",
        "no_follow": true,
        "num_reports": 0,
        "parent_id": "t1_kd6cylj",
        "permalink": "/r/zocken/comments/18hfmoq/suche_wen_zum_zocken_1_2_die_woche_abends_ca_nach/kd6yl7x/",
        "removal_reason": null,
        "replies": "",
        "report_reasons": [],
        "retrieved_on": 1702483076,
        "saved": false,
        "score": 1,
        "score_hidden": false,
        "send_replies": true,
        "stickied": false,
        "subreddit": "zocken",
        "subreddit_id": "t5_2vz1s",
        "subreddit_name_prefixed": "r/zocken",
        "subreddit_type": "public",
        "top_awarded_type": null,
        "total_awards_received": 0,
        "treatment_tags": [],
        "unrepliable_reason": null,
        "updated_on": 1702483092,
        "ups": 1,
        "user_reports": [],
        "responses": []
    },
    {
        "_meta": {
            "retrieved_2nd_on": 1702612684
        },
        "all_awardings": [],
        "approved_at_utc": null,
        "approved_by": null,
        "archived": false,
        "associated_award": null,
        "author": "IxdrowZeexI",
        "author_flair_background_color": null,
        "author_flair_css_class": null,
        "author_flair_richtext": [],
        "author_flair_template_id": null,
        "author_flair_text": null,
        "author_flair_text_color": null,
        "author_flair_type": "text",
        "author_fullname": "t2_ekysb",
        "author_is_blocked": false,
        "author_patreon_flair": false,
        "author_premium": false,
        "awarders": [],
        "banned_at_utc": null,
        "banned_by": null,
        "body": "Schade, 3rd Person ist leider ein absolutes no-go f\u00fcr mich ;(",
        "can_gild": false,
        "can_mod_post": false,
        "collapsed": false,
        "collapsed_because_crowd_control": null,
        "collapsed_reason": null,
        "collapsed_reason_code": null,
        "comment_type": null,
        "controversiality": 0,
        "created": 1702483077.0,
        "created_utc": 1702483077.0,
        "distinguished": null,
        "downs": 0,
        "edited": false,
        "gilded": 0,
        "gildings": {},
        "id": "kd6ymtz",
        "is_submitter": false,
        "likes": null,
        "link_id": "t3_18hfmoq",
        "locked": false,
        "mod_note": null,
        "mod_reason_by": null,
        "mod_reason_title": null,
        "mod_reports": [],
        "name": "t1_kd6ymtz",
        "no_follow": true,
        "num_reports": 0,
        "parent_id": "t1_kd6xcde",
        "permalink": "/r/zocken/comments/18hfmoq/suche_wen_zum_zocken_1_2_die_woche_abends_ca_nach/kd6ymtz/",
        "removal_reason": null,
        "replies": "",
        "report_reasons": [],
        "retrieved_on": 1702483095,
        "saved": false,
        "score": -1,
        "score_hidden": false,
        "send_replies": true,
        "stickied": false,
        "subreddit": "zocken",
        "subreddit_id": "t5_2vz1s",
        "subreddit_name_prefixed": "r/zocken",
        "subreddit_type": "public",
        "top_awarded_type": null,
        "total_awards_received": 0,
        "treatment_tags": [],
        "unrepliable_reason": null,
        "updated_on": 1702483109,
        "ups": -1,
        "user_reports": [],
        "responses": []
    },
    {
        "_meta": {
            "retrieved_2nd_on": 1702612765
        },
        "all_awardings": [],
        "approved_at_utc": null,
        "approved_by": null,
        "archived": false,
        "associated_award": null,
        "author": "Ieaki-98",
        "author_flair_background_color": null,
        "author_flair_css_class": null,
        "author_flair_richtext": [],
        "author_flair_template_id": null,
        "author_flair_text": null,
        "author_flair_text_color": null,
        "author_flair_type": "text",
        "author_fullname": "t2_p84wqw17w",
        "author_is_blocked": false,
        "author_patreon_flair": false,
        "author_premium": false,
        "awarders": [],
        "banned_at_utc": null,
        "banned_by": null,
        "body": "Kenne mich mit dem Serverhopping nicht aus ^^",
        "can_gild": false,
        "can_mod_post": false,
        "collapsed": false,
        "collapsed_because_crowd_control": null,
        "collapsed_reason": null,
        "collapsed_reason_code": null,
        "comment_type": null,
        "controversiality": 0,
        "created": 1702483158.0,
        "created_utc": 1702483158.0,
        "distinguished": null,
        "downs": 0,
        "edited": false,
        "gilded": 0,
        "gildings": {},
        "id": "kd6yufx",
        "is_submitter": false,
        "likes": null,
        "link_id": "t3_18hfmoq",
        "locked": false,
        "mod_note": null,
        "mod_reason_by": null,
        "mod_reason_title": null,
        "mod_reports": [],
        "name": "t1_kd6yufx",
        "no_follow": true,
        "num_reports": 0,
        "parent_id": "t1_kd6yl7x",
        "permalink": "/r/zocken/comments/18hfmoq/suche_wen_zum_zocken_1_2_die_woche_abends_ca_nach/kd6yufx/",
        "removal_reason": null,
        "replies": "",
        "report_reasons": [],
        "retrieved_on": 1702483172,
        "saved": false,
        "score": 2,
        "score_hidden": false,
        "send_replies": true,
        "stickied": false,
        "subreddit": "zocken",
        "subreddit_id": "t5_2vz1s",
        "subreddit_name_prefixed": "r/zocken",
        "subreddit_type": "public",
        "top_awarded_type": null,
        "total_awards_received": 0,
        "treatment_tags": [],
        "unrepliable_reason": null,
        "updated_on": 1702483188,
        "ups": 2,
        "user_reports": [],
        "responses": []
    },
    {
        "_meta": {
            "retrieved_2nd_on": 1702613118
        },
        "all_awardings": [],
        "approved_at_utc": null,
        "approved_by": null,
        "archived": false,
        "associated_award": null,
        "author": "OkCare1776",
        "author_flair_background_color": null,
        "author_flair_css_class": null,
        "author_flair_richtext": [],
        "author_flair_template_id": null,
        "author_flair_text": null,
        "author_flair_text_color": null,
        "author_flair_type": "text",
        "author_fullname": "t2_479rm5eh",
        "author_is_blocked": false,
        "author_patreon_flair": false,
        "author_premium": false,
        "awarders": [],
        "banned_at_utc": null,
        "banned_by": null,
        "body": "Oh okay. Du machst das beim Einloggen. Sobald Du zur Charakterauswahl kommst. Rechtsclick auf Deinen Namen und dann kannst Du das Datenzentrum wechseln. Dann loggt Dich das System dort ein. Ist praktisch. Ich spiele auf Chaos, aber party finder auf light bietet einfach mehr Auswahl",
        "can_gild": false,
        "can_mod_post": false,
        "collapsed": false,
        "collapsed_because_crowd_control": null,
        "collapsed_reason": null,
        "collapsed_reason_code": null,
        "comment_type": null,
        "controversiality": 0,
        "created": 1702483511.0,
        "created_utc": 1702483511.0,
        "distinguished": null,
        "downs": 0,
        "edited": false,
        "gilded": 0,
        "gildings": {},
        "id": "kd6zrdg",
        "is_submitter": false,
        "likes": null,
        "link_id": "t3_18hfmoq",
        "locked": false,
        "mod_note": null,
        "mod_reason_by": null,
        "mod_reason_title": null,
        "mod_reports": [],
        "name": "t1_kd6zrdg",
        "no_follow": true,
        "num_reports": 0,
        "parent_id": "t1_kd6yufx",
        "permalink": "/r/zocken/comments/18hfmoq/suche_wen_zum_zocken_1_2_die_woche_abends_ca_nach/kd6zrdg/",
        "removal_reason": null,
        "replies": "",
        "report_reasons": [],
        "retrieved_on": 1702483532,
        "saved": false,
        "score": 1,
        "score_hidden": false,
        "send_replies": true,
        "stickied": false,
        "subreddit": "zocken",
        "subreddit_id": "t5_2vz1s",
        "subreddit_name_prefixed": "r/zocken",
        "subreddit_type": "public",
        "top_awarded_type": null,
        "total_awards_received": 0,
        "treatment_tags": [],
        "unrepliable_reason": null,
        "updated_on": 1702483542,
        "ups": 1,
        "user_reports": [],
        "responses": []
    },
    {
        "_meta": {
            "retrieved_2nd_on": 1702613493
        },
        "all_awardings": [],
        "approved_at_utc": null,
        "approved_by": null,
        "archived": false,
        "associated_award": null,
        "author": "TrailerparkFairy",
        "author_flair_background_color": null,
        "author_flair_css_class": null,
        "author_flair_richtext": [],
        "author_flair_template_id": null,
        "author_flair_text": null,
        "author_flair_text_color": null,
        "author_flair_type": "text",
        "author_fullname": "t2_r0jdjwpd",
        "author_is_blocked": false,
        "author_patreon_flair": false,
        "author_premium": false,
        "awarders": [],
        "banned_at_utc": null,
        "banned_by": null,
        "body": "Bei GW2 w\u00e4re ich dabei. Spiele es nicht mehr so aktiv, aber casual w\u00e4re okay. Discord ist vorhanden",
        "can_gild": false,
        "can_mod_post": false,
        "collapsed": false,
        "collapsed_because_crowd_control": null,
        "collapsed_reason": null,
        "collapsed_reason_code": null,
        "comment_type": null,
        "controversiality": 0,
        "created": 1702483885.0,
        "created_utc": 1702483885.0,
        "distinguished": null,
        "downs": 0,
        "edited": false,
        "gilded": 0,
        "gildings": {},
        "id": "kd70qox",
        "is_submitter": false,
        "likes": null,
        "link_id": "t3_18hfmoq",
        "locked": false,
        "mod_note": null,
        "mod_reason_by": null,
        "mod_reason_title": null,
        "mod_reports": [],
        "name": "t1_kd70qox",
        "no_follow": true,
        "num_reports": 0,
        "parent_id": "t3_18hfmoq",
        "permalink": "/r/zocken/comments/18hfmoq/suche_wen_zum_zocken_1_2_die_woche_abends_ca_nach/kd70qox/",
        "removal_reason": null,
        "replies": "",
        "report_reasons": [],
        "retrieved_on": 1702483900,
        "saved": false,
        "score": 1,
        "score_hidden": false,
        "send_replies": true,
        "stickied": false,
        "subreddit": "zocken",
        "subreddit_id": "t5_2vz1s",
        "subreddit_name_prefixed": "r/zocken",
        "subreddit_type": "public",
        "top_awarded_type": null,
        "total_awards_received": 0,
        "treatment_tags": [],
        "unrepliable_reason": null,
        "updated_on": 1702483916,
        "ups": 1,
        "user_reports": [],
        "responses": []
    },
    {
        "_meta": {
            "retrieved_2nd_on": 1702613546
        },
        "all_awardings": [],
        "approved_at_utc": null,
        "approved_by": null,
        "archived": false,
        "associated_award": null,
        "author": "maytima",
        "author_flair_background_color": null,
        "author_flair_css_class": null,
        "author_flair_richtext": [],
        "author_flair_template_id": null,
        "author_flair_text": null,
        "author_flair_text_color": null,
        "author_flair_type": "text",
        "author_fullname": "t2_5if77vc1",
        "author_is_blocked": false,
        "author_patreon_flair": false,
        "author_premium": false,
        "awarders": [],
        "banned_at_utc": null,
        "banned_by": null,
        "body": "Baldurs Gate 3 ist mein Vorschlag. Liebevoll gemachtes Spiel mit guter Musik und spannenden Geschichten.",
        "can_gild": false,
        "can_mod_post": false,
        "collapsed": false,
        "collapsed_because_crowd_control": null,
        "collapsed_reason": null,
        "collapsed_reason_code": null,
        "comment_type": null,
        "controversiality": 0,
        "created": 1702483939.0,
        "created_utc": 1702483939.0,
        "distinguished": null,
        "downs": 0,
        "edited": false,
        "gilded": 0,
        "gildings": {},
        "id": "kd70vrv",
        "is_submitter": false,
        "likes": null,
        "link_id": "t3_18hfmoq",
        "locked": false,
        "mod_note": null,
        "mod_reason_by": null,
        "mod_reason_title": null,
        "mod_reports": [],
        "name": "t1_kd70vrv",
        "no_follow": true,
        "num_reports": 0,
        "parent_id": "t3_18hfmoq",
        "permalink": "/r/zocken/comments/18hfmoq/suche_wen_zum_zocken_1_2_die_woche_abends_ca_nach/kd70vrv/",
        "removal_reason": null,
        "replies": "",
        "report_reasons": [],
        "retrieved_on": 1702483955,
        "saved": false,
        "score": 1,
        "score_hidden": false,
        "send_replies": true,
        "stickied": false,
        "subreddit": "zocken",
        "subreddit_id": "t5_2vz1s",
        "subreddit_name_prefixed": "r/zocken",
        "subreddit_type": "public",
        "top_awarded_type": null,
        "total_awards_received": 0,
        "treatment_tags": [],
        "unrepliable_reason": null,
        "updated_on": 1702483970,
        "ups": 1,
        "user_reports": [],
        "responses": []
    },
    {
        "_meta": {
            "retrieved_2nd_on": 1702613668
        },
        "all_awardings": [],
        "approved_at_utc": null,
        "approved_by": null,
        "archived": false,
        "associated_award": null,
        "author": "Pale-Grapefruit-7802",
        "author_flair_background_color": null,
        "author_flair_css_class": null,
        "author_flair_richtext": [],
        "author_flair_template_id": null,
        "author_flair_text": null,
        "author_flair_text_color": null,
        "author_flair_type": "text",
        "author_fullname": "t2_nxy4dsjc",
        "author_is_blocked": false,
        "author_patreon_flair": false,
        "author_premium": false,
        "awarders": [],
        "banned_at_utc": null,
        "banned_by": null,
        "body": "Ja. Ich wei\u00df noch nicht ob ich damit warm werde. Eigentlich gefallen mir rundenbasierte K\u00e4mpfe. Aber dann eher offline so ala Magic. War offline auch nie ein D&D Spieler",
        "can_gild": false,
        "can_mod_post": false,
        "collapsed": false,
        "collapsed_because_crowd_control": null,
        "collapsed_reason": null,
        "collapsed_reason_code": null,
        "comment_type": null,
        "controversiality": 0,
        "created": 1702484060.0,
        "created_utc": 1702484060.0,
        "distinguished": null,
        "downs": 0,
        "edited": false,
        "gilded": 0,
        "gildings": {},
        "id": "kd717cq",
        "is_submitter": true,
        "likes": null,
        "link_id": "t3_18hfmoq",
        "locked": false,
        "mod_note": null,
        "mod_reason_by": null,
        "mod_reason_title": null,
        "mod_reports": [],
        "name": "t1_kd717cq",
        "no_follow": true,
        "num_reports": 0,
        "parent_id": "t1_kd70vrv",
        "permalink": "/r/zocken/comments/18hfmoq/suche_wen_zum_zocken_1_2_die_woche_abends_ca_nach/kd717cq/",
        "removal_reason": null,
        "replies": "",
        "report_reasons": [],
        "retrieved_on": 1702484077,
        "saved": false,
        "score": 1,
        "score_hidden": false,
        "send_replies": true,
        "stickied": false,
        "subreddit": "zocken",
        "subreddit_id": "t5_2vz1s",
        "subreddit_name_prefixed": "r/zocken",
        "subreddit_type": "public",
        "top_awarded_type": null,
        "total_awards_received": 0,
        "treatment_tags": [],
        "unrepliable_reason": null,
        "updated_on": 1702484091,
        "ups": 1,
        "user_reports": [],
        "responses": []
    },
    {
        "_meta": {
            "retrieved_2nd_on": 1702613686
        },
        "all_awardings": [],
        "approved_at_utc": null,
        "approved_by": null,
        "archived": false,
        "associated_award": null,
        "author": "Ieaki-98",
        "author_flair_background_color": null,
        "author_flair_css_class": null,
        "author_flair_richtext": [],
        "author_flair_template_id": null,
        "author_flair_text": null,
        "author_flair_text_color": null,
        "author_flair_type": "text",
        "author_fullname": "t2_p84wqw17w",
        "author_is_blocked": false,
        "author_patreon_flair": false,
        "author_premium": false,
        "awarders": [],
        "banned_at_utc": null,
        "banned_by": null,
        "body": "Hab das nie gebraucht, daher auch nicht benutzt ^^\n\nAber gut zu wissen, dass es easy ist :D",
        "can_gild": false,
        "can_mod_post": false,
        "collapsed": false,
        "collapsed_because_crowd_control": null,
        "collapsed_reason": null,
        "collapsed_reason_code": null,
        "comment_type": null,
        "controversiality": 0,
        "created": 1702484077.0,
        "created_utc": 1702484077.0,
        "distinguished": null,
        "downs": 0,
        "edited": false,
        "gilded": 0,
        "gildings": {},
        "id": "kd718zu",
        "is_submitter": false,
        "likes": null,
        "link_id": "t3_18hfmoq",
        "locked": false,
        "mod_note": null,
        "mod_reason_by": null,
        "mod_reason_title": null,
        "mod_reports": [],
        "name": "t1_kd718zu",
        "no_follow": true,
        "num_reports": 0,
        "parent_id": "t1_kd6zrdg",
        "permalink": "/r/zocken/comments/18hfmoq/suche_wen_zum_zocken_1_2_die_woche_abends_ca_nach/kd718zu/",
        "removal_reason": null,
        "replies": "",
        "report_reasons": [],
        "retrieved_on": 1702484093,
        "saved": false,
        "score": 1,
        "score_hidden": false,
        "send_replies": true,
        "stickied": false,
        "subreddit": "zocken",
        "subreddit_id": "t5_2vz1s",
        "subreddit_name_prefixed": "r/zocken",
        "subreddit_type": "public",
        "top_awarded_type": null,
        "total_awards_received": 0,
        "treatment_tags": [],
        "unrepliable_reason": null,
        "updated_on": 1702484108,
        "ups": 1,
        "user_reports": [],
        "responses": []
    },
    {
        "_meta": {
            "retrieved_2nd_on": 1702616082
        },
        "all_awardings": [],
        "approved_at_utc": null,
        "approved_by": null,
        "archived": false,
        "associated_award": null,
        "author": "PhantomM123",
        "author_flair_background_color": null,
        "author_flair_css_class": null,
        "author_flair_richtext": [],
        "author_flair_template_id": null,
        "author_flair_text": null,
        "author_flair_text_color": null,
        "author_flair_type": "text",
        "author_fullname": "t2_a3vsi9ge",
        "author_is_blocked": false,
        "author_patreon_flair": false,
        "author_premium": false,
        "awarders": [],
        "banned_at_utc": null,
        "banned_by": null,
        "body": "Wenn du noch wen suchst, melde dich. Passt von Alter und Uhrzeit denke ich ganz gut.\n\nW\u00e4re bei Aufbau/Survival dabei. Letztens gezockt und Multiplayer geeignet: Anno, EU4, Don't Starve together, Stardew Valley, Victoria 3, Divinity original sins 2. Baldurs Gate k\u00f6nnte ich mir auch gut vorstellen.",
        "can_gild": false,
        "can_mod_post": false,
        "collapsed": false,
        "collapsed_because_crowd_control": null,
        "collapsed_reason": null,
        "collapsed_reason_code": null,
        "comment_type": null,
        "controversiality": 0,
        "created": 1702486472.0,
        "created_utc": 1702486472.0,
        "distinguished": null,
        "downs": 0,
        "edited": false,
        "gilded": 0,
        "gildings": {},
        "id": "kd77q1b",
        "is_submitter": false,
        "likes": null,
        "link_id": "t3_18hfmoq",
        "locked": false,
        "mod_note": null,
        "mod_reason_by": null,
        "mod_reason_title": null,
        "mod_reports": [],
        "name": "t1_kd77q1b",
        "no_follow": true,
        "num_reports": 0,
        "parent_id": "t3_18hfmoq",
        "permalink": "/r/zocken/comments/18hfmoq/suche_wen_zum_zocken_1_2_die_woche_abends_ca_nach/kd77q1b/",
        "removal_reason": null,
        "replies": "",
        "report_reasons": [],
        "retrieved_on": 1702486486,
        "saved": false,
        "score": 1,
        "score_hidden": false,
        "send_replies": true,
        "stickied": false,
        "subreddit": "zocken",
        "subreddit_id": "t5_2vz1s",
        "subreddit_name_prefixed": "r/zocken",
        "subreddit_type": "public",
        "top_awarded_type": null,
        "total_awards_received": 0,
        "treatment_tags": [],
        "unrepliable_reason": null,
        "updated_on": 1702486503,
        "ups": 1,
        "user_reports": [],
        "responses": []
    },
    {
        "_meta": {
            "retrieved_2nd_on": 1702630732
        },
        "all_awardings": [],
        "approved_at_utc": null,
        "approved_by": null,
        "archived": false,
        "associated_award": null,
        "author": "Chafaris_DE",
        "author_flair_background_color": null,
        "author_flair_css_class": null,
        "author_flair_richtext": [],
        "author_flair_template_id": null,
        "author_flair_text": null,
        "author_flair_text_color": null,
        "author_flair_type": "text",
        "author_fullname": "t2_cn6f1yia",
        "author_is_blocked": false,
        "author_patreon_flair": false,
        "author_premium": false,
        "awarders": [],
        "banned_at_utc": null,
        "banned_by": null,
        "body": "Also ich spiele aktiv FFXIV, bin 41 und ebenfalls unter der Woche mal ab 20.00 Uhr und gerne auch mal sporadisch am Wochenende online.\n\nMeld dich einfach hier oder per PN wenn du m\u00f6chtest. Ob frisch in FFXIV oder alter Hase ich helfe gerne aus und bin f\u00fcr jeden Quatsch zu haben \ud83e\udd17",
        "can_gild": false,
        "can_mod_post": false,
        "collapsed": false,
        "collapsed_because_crowd_control": null,
        "collapsed_reason": null,
        "collapsed_reason_code": null,
        "comment_type": null,
        "controversiality": 0,
        "created": 1702501113.0,
        "created_utc": 1702501113.0,
        "distinguished": null,
        "downs": 0,
        "edited": false,
        "gilded": 0,
        "gildings": {},
        "id": "kd8a5as",
        "is_submitter": false,
        "likes": null,
        "link_id": "t3_18hfmoq",
        "locked": false,
        "mod_note": null,
        "mod_reason_by": null,
        "mod_reason_title": null,
        "mod_reports": [],
        "name": "t1_kd8a5as",
        "no_follow": true,
        "num_reports": 0,
        "parent_id": "t3_18hfmoq",
        "permalink": "/r/zocken/comments/18hfmoq/suche_wen_zum_zocken_1_2_die_woche_abends_ca_nach/kd8a5as/",
        "removal_reason": null,
        "replies": "",
        "report_reasons": [],
        "retrieved_on": 1702501132,
        "saved": false,
        "score": 1,
        "score_hidden": false,
        "send_replies": true,
        "stickied": false,
        "subreddit": "zocken",
        "subreddit_id": "t5_2vz1s",
        "subreddit_name_prefixed": "r/zocken",
        "subreddit_type": "public",
        "top_awarded_type": null,
        "total_awards_received": 0,
        "treatment_tags": [],
        "unrepliable_reason": null,
        "updated_on": 1702501144,
        "ups": 1,
        "user_reports": [],
        "responses": []
    },
    {
        "_meta": {
            "removal_type": "removed",
            "retrieved_2nd_on": 1702635554,
            "was_deleted_later": true
        },
        "all_awardings": [],
        "approved_at_utc": null,
        "approved_by": null,
        "archived": false,
        "associated_award": null,
        "author": "AccomplishedHat3167",
        "author_flair_background_color": null,
        "author_flair_css_class": null,
        "author_flair_richtext": [],
        "author_flair_template_id": null,
        "author_flair_text": null,
        "author_flair_text_color": "dark",
        "author_flair_type": "text",
        "author_fullname": "t2_pvvk2gk6p",
        "author_is_blocked": false,
        "author_patreon_flair": false,
        "author_premium": false,
        "awarders": [],
        "banned_at_utc": null,
        "banned_by": null,
        "body": "J",
        "can_gild": false,
        "can_mod_post": false,
        "collapsed": false,
        "collapsed_because_crowd_control": null,
        "collapsed_reason": null,
        "collapsed_reason_code": null,
        "comment_type": null,
        "controversiality": 0,
        "created": 1702505815.0,
        "created_utc": 1702505815.0,
        "distinguished": null,
        "downs": 0,
        "edited": false,
        "gilded": 0,
        "gildings": {},
        "id": "kd8mw7p",
        "is_submitter": false,
        "likes": null,
        "link_id": "t3_18hfmoq",
        "locked": false,
        "mod_note": null,
        "mod_reason_by": null,
        "mod_reason_title": null,
        "mod_reports": [],
        "name": "t1_kd8mw7p",
        "no_follow": true,
        "num_reports": 0,
        "parent_id": "t3_18hfmoq",
        "permalink": "/r/zocken/comments/18hfmoq/suche_wen_zum_zocken_1_2_die_woche_abends_ca_nach/kd8mw7p/",
        "removal_reason": null,
        "replies": "",
        "report_reasons": [],
        "retrieved_on": 1702505833,
        "saved": false,
        "score": 1,
        "score_hidden": false,
        "send_replies": true,
        "stickied": false,
        "subreddit": "zocken",
        "subreddit_id": "t5_2vz1s",
        "subreddit_name_prefixed": "r/zocken",
        "subreddit_type": "public",
        "top_awarded_type": null,
        "total_awards_received": 0,
        "treatment_tags": [],
        "unrepliable_reason": null,
        "updated_on": 1702505846,
        "ups": 1,
        "user_reports": [],
        "responses": []
    }
]