[
    {
        "_meta": {
            "retrieved_2nd_on": 1700294816
        },
        "all_awardings": [],
        "approved_at_utc": null,
        "approved_by": null,
        "archived": false,
        "associated_award": null,
        "author": "Ambitious-Tower131",
        "author_flair_background_color": null,
        "author_flair_css_class": null,
        "author_flair_richtext": [],
        "author_flair_template_id": null,
        "author_flair_text": null,
        "author_flair_text_color": null,
        "author_flair_type": "text",
        "author_fullname": "t2_fg9h9zfwy",
        "author_is_blocked": false,
        "author_patreon_flair": false,
        "author_premium": false,
        "awarders": [],
        "banned_at_utc": null,
        "banned_by": null,
        "body": "ING eventuell?",
        "can_gild": false,
        "can_mod_post": false,
        "collapsed": false,
        "collapsed_because_crowd_control": null,
        "collapsed_reason": null,
        "collapsed_reason_code": null,
        "comment_type": null,
        "controversiality": 0,
        "created": 1699100177.0,
        "created_utc": 1699100177.0,
        "distinguished": null,
        "downs": 0,
        "edited": false,
        "gilded": 0,
        "gildings": {},
        "id": "k7s1w51",
        "is_submitter": false,
        "likes": null,
        "link_id": "t3_17nk88j",
        "locked": false,
        "mod_note": null,
        "mod_reason_by": null,
        "mod_reason_title": null,
        "mod_reports": [],
        "name": "t1_k7s1w51",
        "no_follow": true,
        "num_reports": 0,
        "parent_id": "t3_17nk88j",
        "permalink": "/r/Finanzen/comments/17nk88j/ein_konto_f\u00fcr_alles/k7s1w51/",
        "removal_reason": null,
        "replies": "",
        "report_reasons": [],
        "retrieved_on": 1699100190,
        "saved": false,
        "score": 15,
        "score_hidden": false,
        "send_replies": true,
        "stickied": false,
        "subreddit": "Finanzen",
        "subreddit_id": "t5_35m5e",
        "subreddit_name_prefixed": "r/Finanzen",
        "subreddit_type": "public",
        "top_awarded_type": null,
        "total_awards_received": 0,
        "treatment_tags": [],
        "unrepliable_reason": null,
        "updated_on": 1699100208,
        "ups": 15,
        "user_reports": [],
        "responses": []
    },
    {
        "_meta": {
            "retrieved_2nd_on": 1700294940
        },
        "all_awardings": [],
        "approved_at_utc": null,
        "approved_by": null,
        "archived": false,
        "associated_award": null,
        "author": "justaverysimpleguy",
        "author_flair_background_color": null,
        "author_flair_css_class": null,
        "author_flair_richtext": [
            {
                "e": "text",
                "t": "DE"
            }
        ],
        "author_flair_template_id": "54daf866-0273-11eb-ac01-0e9e2216ce81",
        "author_flair_text": "DE",
        "author_flair_text_color": "dark",
        "author_flair_type": "richtext",
        "author_fullname": "t2_2z914321",
        "author_is_blocked": false,
        "author_patreon_flair": false,
        "author_premium": true,
        "awarders": [],
        "banned_at_utc": null,
        "banned_by": null,
        "body": "ING ist die Beste und wird hier sehr oft empfohlen. Nur die Tagesgeldzinsen sind sehr mau, aber da kann man sich ja mit wenig Aufwand ein Tagesgeldkonto (bspw. Barclays oder auch C24) klicken.",
        "can_gild": false,
        "can_mod_post": false,
        "collapsed": false,
        "collapsed_because_crowd_control": null,
        "collapsed_reason": null,
        "collapsed_reason_code": null,
        "comment_type": null,
        "controversiality": 0,
        "created": 1699100426.0,
        "created_utc": 1699100426.0,
        "distinguished": null,
        "downs": 0,
        "edited": false,
        "gilded": 0,
        "gildings": {},
        "id": "k7s2btm",
        "is_submitter": false,
        "likes": null,
        "link_id": "t3_17nk88j",
        "locked": false,
        "mod_note": null,
        "mod_reason_by": null,
        "mod_reason_title": null,
        "mod_reports": [],
        "name": "t1_k7s2btm",
        "no_follow": true,
        "num_reports": 0,
        "parent_id": "t3_17nk88j",
        "permalink": "/r/Finanzen/comments/17nk88j/ein_konto_f\u00fcr_alles/k7s2btm/",
        "removal_reason": null,
        "replies": "",
        "report_reasons": [],
        "retrieved_on": 1699100443,
        "saved": false,
        "score": 10,
        "score_hidden": false,
        "send_replies": true,
        "stickied": false,
        "subreddit": "Finanzen",
        "subreddit_id": "t5_35m5e",
        "subreddit_name_prefixed": "r/Finanzen",
        "subreddit_type": "public",
        "top_awarded_type": null,
        "total_awards_received": 0,
        "treatment_tags": [],
        "unrepliable_reason": null,
        "updated_on": 1699100458,
        "ups": 10,
        "user_reports": [],
        "responses": []
    },
    {
        "_meta": {
            "is_edited": true,
            "retrieved_2nd_on": 1700295290
        },
        "all_awardings": [],
        "approved_at_utc": null,
        "approved_by": null,
        "archived": false,
        "associated_award": null,
        "author": "_2l5_",
        "author_flair_background_color": null,
        "author_flair_css_class": null,
        "author_flair_richtext": [],
        "author_flair_template_id": null,
        "author_flair_text": null,
        "author_flair_text_color": null,
        "author_flair_type": "text",
        "author_fullname": "t2_iyjxmdeq",
        "author_is_blocked": false,
        "author_patreon_flair": false,
        "author_premium": false,
        "awarders": [],
        "banned_at_utc": null,
        "banned_by": null,
        "body": "C24 ist f\u00fcr die Neukunden nicht mehr interessant. Falls ich mich nicht irre sind es nur 1,75% (Bestandkunden 4%) auf Tagesgeld und 2% auf Giro.",
        "can_gild": false,
        "can_mod_post": false,
        "collapsed": false,
        "collapsed_because_crowd_control": null,
        "collapsed_reason": null,
        "collapsed_reason_code": null,
        "comment_type": null,
        "controversiality": 0,
        "created": 1699101104.0,
        "created_utc": 1699101104.0,
        "distinguished": null,
        "downs": 0,
        "edited": 1699104006.0,
        "gilded": 0,
        "gildings": {},
        "id": "k7s3jtz",
        "is_submitter": false,
        "likes": null,
        "link_id": "t3_17nk88j",
        "locked": false,
        "mod_note": null,
        "mod_reason_by": null,
        "mod_reason_title": null,
        "mod_reports": [],
        "name": "t1_k7s3jtz",
        "no_follow": true,
        "num_reports": 0,
        "parent_id": "t1_k7s2btm",
        "permalink": "/r/Finanzen/comments/17nk88j/ein_konto_f\u00fcr_alles/k7s3jtz/",
        "removal_reason": null,
        "replies": "",
        "report_reasons": [],
        "retrieved_on": 1699101121,
        "saved": false,
        "score": 3,
        "score_hidden": false,
        "send_replies": true,
        "stickied": false,
        "subreddit": "Finanzen",
        "subreddit_id": "t5_35m5e",
        "subreddit_name_prefixed": "r/Finanzen",
        "subreddit_type": "public",
        "top_awarded_type": null,
        "total_awards_received": 0,
        "treatment_tags": [],
        "unrepliable_reason": null,
        "updated_on": 1699101135,
        "ups": 3,
        "user_reports": [],
        "responses": []
    },
    {
        "_meta": {
            "is_edited": true,
            "retrieved_2nd_on": 1700295686
        },
        "all_awardings": [],
        "approved_at_utc": null,
        "approved_by": null,
        "archived": false,
        "associated_award": null,
        "author": "EmptyImagination4",
        "author_flair_background_color": null,
        "author_flair_css_class": null,
        "author_flair_richtext": [],
        "author_flair_template_id": null,
        "author_flair_text": null,
        "author_flair_text_color": null,
        "author_flair_type": "text",
        "author_fullname": "t2_66zsbkc9",
        "author_is_blocked": false,
        "author_patreon_flair": false,
        "author_premium": false,
        "awarders": [],
        "banned_at_utc": null,
        "banned_by": null,
        "body": "ok, das ist interssant! Grio ist kostenlos. Ja Tagesgeld ist eher Mau mit 1,25% oder so nach ablauf der Aktion ... wie ist das mit den Depotgeb\u00fchren. ist ja irgendwie 5\u20ac pro Order +0,25% des Orderwerts. Also so .. ok. Es gibt auch die verg\u00fcnstigten ETF Sparpl\u00e4ne, aber hier wei\u00df man nicht so recht, wie viel die dann kosten?",
        "can_gild": false,
        "can_mod_post": false,
        "collapsed": false,
        "collapsed_because_crowd_control": null,
        "collapsed_reason": null,
        "collapsed_reason_code": null,
        "comment_type": null,
        "controversiality": 0,
        "created": 1699101857.0,
        "created_utc": 1699101857.0,
        "distinguished": null,
        "downs": 0,
        "edited": 1699102080.0,
        "gilded": 0,
        "gildings": {},
        "id": "k7s4z1y",
        "is_submitter": true,
        "likes": null,
        "link_id": "t3_17nk88j",
        "locked": false,
        "mod_note": null,
        "mod_reason_by": null,
        "mod_reason_title": null,
        "mod_reports": [],
        "name": "t1_k7s4z1y",
        "no_follow": true,
        "num_reports": 0,
        "parent_id": "t1_k7s2btm",
        "permalink": "/r/Finanzen/comments/17nk88j/ein_konto_f\u00fcr_alles/k7s4z1y/",
        "removal_reason": null,
        "replies": "",
        "report_reasons": [],
        "retrieved_on": 1699101875,
        "saved": false,
        "score": 1,
        "score_hidden": false,
        "send_replies": true,
        "stickied": false,
        "subreddit": "Finanzen",
        "subreddit_id": "t5_35m5e",
        "subreddit_name_prefixed": "r/Finanzen",
        "subreddit_type": "public",
        "top_awarded_type": null,
        "total_awards_received": 0,
        "treatment_tags": [],
        "unrepliable_reason": null,
        "updated_on": 1699101887,
        "ups": 1,
        "user_reports": [],
        "responses": []
    },
    {
        "_meta": {
            "retrieved_2nd_on": 1700296145
        },
        "all_awardings": [],
        "approved_at_utc": null,
        "approved_by": null,
        "archived": false,
        "associated_award": null,
        "author": "JustATr8er",
        "author_flair_background_color": null,
        "author_flair_css_class": null,
        "author_flair_richtext": [],
        "author_flair_template_id": null,
        "author_flair_text": null,
        "author_flair_text_color": null,
        "author_flair_type": "text",
        "author_fullname": "t2_a7zb7b4j",
        "author_is_blocked": false,
        "author_patreon_flair": false,
        "author_premium": false,
        "awarders": [],
        "banned_at_utc": null,
        "banned_by": null,
        "body": "ETF Sparpl\u00e4ne sind kostenlos.",
        "can_gild": false,
        "can_mod_post": false,
        "collapsed": false,
        "collapsed_because_crowd_control": null,
        "collapsed_reason": null,
        "collapsed_reason_code": null,
        "comment_type": null,
        "controversiality": 0,
        "created": 1699102654.0,
        "created_utc": 1699102654.0,
        "distinguished": null,
        "downs": 0,
        "edited": false,
        "gilded": 0,
        "gildings": {},
        "id": "k7s6jeb",
        "is_submitter": false,
        "likes": null,
        "link_id": "t3_17nk88j",
        "locked": false,
        "mod_note": null,
        "mod_reason_by": null,
        "mod_reason_title": null,
        "mod_reports": [],
        "name": "t1_k7s6jeb",
        "no_follow": true,
        "num_reports": 0,
        "parent_id": "t1_k7s4z1y",
        "permalink": "/r/Finanzen/comments/17nk88j/ein_konto_f\u00fcr_alles/k7s6jeb/",
        "removal_reason": null,
        "replies": "",
        "report_reasons": [],
        "retrieved_on": 1699102667,
        "saved": false,
        "score": 3,
        "score_hidden": false,
        "send_replies": true,
        "stickied": false,
        "subreddit": "Finanzen",
        "subreddit_id": "t5_35m5e",
        "subreddit_name_prefixed": "r/Finanzen",
        "subreddit_type": "public",
        "top_awarded_type": null,
        "total_awards_received": 0,
        "treatment_tags": [],
        "unrepliable_reason": null,
        "updated_on": 1699102684,
        "ups": 3,
        "user_reports": [],
        "responses": []
    },
    {
        "_meta": {
            "removal_type": "deleted",
            "retrieved_2nd_on": 1700296567,
            "was_deleted_later": true
        },
        "all_awardings": [],
        "approved_at_utc": null,
        "approved_by": null,
        "archived": false,
        "associated_award": null,
        "author": "_2l5_",
        "author_flair_background_color": null,
        "author_flair_css_class": null,
        "author_flair_richtext": [],
        "author_flair_template_id": null,
        "author_flair_text": null,
        "author_flair_text_color": "dark",
        "author_flair_type": "text",
        "author_fullname": "t2_iyjxmdeq",
        "author_is_blocked": false,
        "author_patreon_flair": false,
        "author_premium": false,
        "awarders": [],
        "banned_at_utc": null,
        "banned_by": null,
        "body": "Konto ist kostenlos, bei aktive Nutzung (2 Lastschriften/Monat) ist auch GiroKarte kostenlos.\nHabe nochmal nachgeschaut, es sind 2% auf Tagesgeld, Giro und Pockets bis 31.12.23. Danach sind die Zinsen variabel: EZB-Zins - 1,5%.= 4,5%-1,5%=3%. Den Vorteil sehe ich daran, dass alle meine Fixkosten bis zur Abbuchung verzinst werden. Auch Kundensupport und Aktualisierung der Zinsen auch an Bestandkunden sollten gut sein. \nVielleicht w\u00e4re die Trade Republic was f\u00fcr dich, es sind 4% p.a. (bis 50k\u20ac) auf nicht investierten Kapital und g\u00fcnstige Ordergeb\u00fchren.",
        "can_gild": false,
        "can_mod_post": false,
        "collapsed": false,
        "collapsed_because_crowd_control": null,
        "collapsed_reason": null,
        "collapsed_reason_code": null,
        "comment_type": null,
        "controversiality": 0,
        "created": 1699103325.0,
        "created_utc": 1699103325.0,
        "distinguished": null,
        "downs": 0,
        "edited": false,
        "gilded": 0,
        "gildings": {},
        "id": "k7s7wgf",
        "is_submitter": false,
        "likes": null,
        "link_id": "t3_17nk88j",
        "locked": false,
        "mod_note": null,
        "mod_reason_by": null,
        "mod_reason_title": null,
        "mod_reports": [],
        "name": "t1_k7s7wgf",
        "no_follow": true,
        "num_reports": 0,
        "parent_id": "t1_k7s4z1y",
        "permalink": "/r/Finanzen/comments/17nk88j/ein_konto_f\u00fcr_alles/k7s7wgf/",
        "removal_reason": null,
        "replies": "",
        "report_reasons": [],
        "retrieved_on": 1699103341,
        "saved": false,
        "score": 1,
        "score_hidden": false,
        "send_replies": true,
        "stickied": false,
        "subreddit": "Finanzen",
        "subreddit_id": "t5_35m5e",
        "subreddit_name_prefixed": "r/Finanzen",
        "subreddit_type": "public",
        "top_awarded_type": null,
        "total_awards_received": 0,
        "treatment_tags": [],
        "unrepliable_reason": null,
        "updated_on": 1699103355,
        "ups": 1,
        "user_reports": [],
        "responses": []
    },
    {
        "_meta": {
            "retrieved_2nd_on": 1700296643
        },
        "all_awardings": [],
        "approved_at_utc": null,
        "approved_by": null,
        "archived": false,
        "associated_award": null,
        "author": "justaverysimpleguy",
        "author_flair_background_color": null,
        "author_flair_css_class": null,
        "author_flair_richtext": [
            {
                "e": "text",
                "t": "DE"
            }
        ],
        "author_flair_template_id": "54daf866-0273-11eb-ac01-0e9e2216ce81",
        "author_flair_text": "DE",
        "author_flair_text_color": "dark",
        "author_flair_type": "richtext",
        "author_fullname": "t2_2z914321",
        "author_is_blocked": false,
        "author_patreon_flair": false,
        "author_premium": true,
        "awarders": [],
        "banned_at_utc": null,
        "banned_by": null,
        "body": "Du sprichst mE von C24 und er von der ING.",
        "can_gild": false,
        "can_mod_post": false,
        "collapsed": false,
        "collapsed_because_crowd_control": null,
        "collapsed_reason": null,
        "collapsed_reason_code": null,
        "comment_type": null,
        "controversiality": 0,
        "created": 1699103461.0,
        "created_utc": 1699103461.0,
        "distinguished": null,
        "downs": 0,
        "edited": false,
        "gilded": 0,
        "gildings": {},
        "id": "k7s86my",
        "is_submitter": false,
        "likes": null,
        "link_id": "t3_17nk88j",
        "locked": false,
        "mod_note": null,
        "mod_reason_by": null,
        "mod_reason_title": null,
        "mod_reports": [],
        "name": "t1_k7s86my",
        "no_follow": true,
        "num_reports": 0,
        "parent_id": "t1_k7s7wgf",
        "permalink": "/r/Finanzen/comments/17nk88j/ein_konto_f\u00fcr_alles/k7s86my/",
        "removal_reason": null,
        "replies": "",
        "report_reasons": [],
        "retrieved_on": 1699103479,
        "saved": false,
        "score": 1,
        "score_hidden": false,
        "send_replies": true,
        "stickied": false,
        "subreddit": "Finanzen",
        "subreddit_id": "t5_35m5e",
        "subreddit_name_prefixed": "r/Finanzen",
        "subreddit_type": "public",
        "top_awarded_type": null,
        "total_awards_received": 0,
        "treatment_tags": [],
        "unrepliable_reason": null,
        "updated_on": 1699103491,
        "ups": 1,
        "user_reports": [],
        "responses": []
    },
    {
        "_meta": {
            "retrieved_2nd_on": 1700296917
        },
        "all_awardings": [],
        "approved_at_utc": null,
        "approved_by": null,
        "archived": false,
        "associated_award": null,
        "author": "_2l5_",
        "author_flair_background_color": null,
        "author_flair_css_class": null,
        "author_flair_richtext": [],
        "author_flair_template_id": null,
        "author_flair_text": null,
        "author_flair_text_color": null,
        "author_flair_type": "text",
        "author_fullname": "t2_iyjxmdeq",
        "author_is_blocked": false,
        "author_patreon_flair": false,
        "author_premium": false,
        "awarders": [],
        "banned_at_utc": null,
        "banned_by": null,
        "body": "Danke f\u00fcr den Hinweis, habe mich vertan :)",
        "can_gild": false,
        "can_mod_post": false,
        "collapsed": false,
        "collapsed_because_crowd_control": null,
        "collapsed_reason": null,
        "collapsed_reason_code": null,
        "comment_type": null,
        "controversiality": 0,
        "created": 1699103952.0,
        "created_utc": 1699103952.0,
        "distinguished": null,
        "downs": 0,
        "edited": false,
        "gilded": 0,
        "gildings": {},
        "id": "k7s97s5",
        "is_submitter": false,
        "likes": null,
        "link_id": "t3_17nk88j",
        "locked": false,
        "mod_note": null,
        "mod_reason_by": null,
        "mod_reason_title": null,
        "mod_reports": [],
        "name": "t1_k7s97s5",
        "no_follow": true,
        "num_reports": 0,
        "parent_id": "t1_k7s86my",
        "permalink": "/r/Finanzen/comments/17nk88j/ein_konto_f\u00fcr_alles/k7s97s5/",
        "removal_reason": null,
        "replies": "",
        "report_reasons": [],
        "retrieved_on": 1699103967,
        "saved": false,
        "score": 1,
        "score_hidden": false,
        "send_replies": true,
        "stickied": false,
        "subreddit": "Finanzen",
        "subreddit_id": "t5_35m5e",
        "subreddit_name_prefixed": "r/Finanzen",
        "subreddit_type": "public",
        "top_awarded_type": null,
        "total_awards_received": 0,
        "treatment_tags": [],
        "unrepliable_reason": null,
        "updated_on": 1699103983,
        "ups": 1,
        "user_reports": [],
        "responses": []
    },
    {
        "_meta": {
            "removal_type": "deleted",
            "retrieved_2nd_on": 1700297359,
            "was_deleted_later": true
        },
        "all_awardings": [],
        "approved_at_utc": null,
        "approved_by": null,
        "archived": false,
        "associated_award": null,
        "author": "SuckerNonSucker",
        "author_flair_background_color": null,
        "author_flair_css_class": null,
        "author_flair_richtext": [],
        "author_flair_template_id": null,
        "author_flair_text": null,
        "author_flair_text_color": null,
        "author_flair_type": "text",
        "author_fullname": "t2_avafqu5s",
        "author_is_blocked": false,
        "author_patreon_flair": false,
        "author_premium": false,
        "awarders": [],
        "banned_at_utc": null,
        "banned_by": null,
        "body": "Sparpl\u00e4ne kosten bei der Comdirect 1,50%. Ordergeb\u00fchren bewegen sich ab 1000% bei rund 1%, je mehr, desto niedriger.\nIst zwar jetzt nicht Neobroker-g\u00fcnstig, aber noch vertretbar. Daf\u00fcr hast du einen vollwertigen Broker mit einer Vielzahl an Handelspl\u00e4tzen, guten und schnellen Service. \nAm Ende immer eine Frage des Komforts. Ich bin seit 2001 bei der Comdirect und ja, da geht auch mal was in die Hose (Steuer\u00fcbersicht 2022 l\u00e4sst gr\u00fc\u00dfen...). Wenn es aber danach geht, dann schie\u00dft jeder Anbieter mal den Bock ab.",
        "can_gild": false,
        "can_mod_post": false,
        "collapsed": false,
        "collapsed_because_crowd_control": null,
        "collapsed_reason": null,
        "collapsed_reason_code": null,
        "comment_type": null,
        "controversiality": 0,
        "created": 1699104696.0,
        "created_utc": 1699104696.0,
        "distinguished": null,
        "downs": 0,
        "edited": false,
        "gilded": 0,
        "gildings": {},
        "id": "k7sat3o",
        "is_submitter": false,
        "likes": null,
        "link_id": "t3_17nk88j",
        "locked": false,
        "mod_note": null,
        "mod_reason_by": null,
        "mod_reason_title": null,
        "mod_reports": [],
        "name": "t1_k7sat3o",
        "no_follow": true,
        "num_reports": 0,
        "parent_id": "t3_17nk88j",
        "permalink": "/r/Finanzen/comments/17nk88j/ein_konto_f\u00fcr_alles/k7sat3o/",
        "removal_reason": null,
        "replies": "",
        "report_reasons": [],
        "retrieved_on": 1699104714,
        "saved": false,
        "score": 4,
        "score_hidden": false,
        "send_replies": true,
        "stickied": false,
        "subreddit": "Finanzen",
        "subreddit_id": "t5_35m5e",
        "subreddit_name_prefixed": "r/Finanzen",
        "subreddit_type": "public",
        "top_awarded_type": null,
        "total_awards_received": 0,
        "treatment_tags": [],
        "unrepliable_reason": null,
        "updated_on": 1699104726,
        "ups": 4,
        "user_reports": [],
        "responses": []
    },
    {
        "_meta": {
            "retrieved_2nd_on": 1700297776
        },
        "all_awardings": [],
        "approved_at_utc": null,
        "approved_by": null,
        "archived": false,
        "associated_award": null,
        "author": "Misgurnus069",
        "author_flair_background_color": null,
        "author_flair_css_class": null,
        "author_flair_richtext": [],
        "author_flair_template_id": null,
        "author_flair_text": null,
        "author_flair_text_color": null,
        "author_flair_type": "text",
        "author_fullname": "t2_mn6r2dgsr",
        "author_is_blocked": false,
        "author_patreon_flair": false,
        "author_premium": false,
        "awarders": [],
        "banned_at_utc": null,
        "banned_by": null,
        "body": "Wenn du wirklich alles bei einer Bank willst, musst du Kompromisse machen. Hohe TG Zinsen gibts eh immer nur tempor\u00e4r.",
        "can_gild": false,
        "can_mod_post": false,
        "collapsed": false,
        "collapsed_because_crowd_control": null,
        "collapsed_reason": null,
        "collapsed_reason_code": null,
        "comment_type": null,
        "controversiality": 0,
        "created": 1699105337.0,
        "created_utc": 1699105337.0,
        "distinguished": null,
        "downs": 0,
        "edited": false,
        "gilded": 0,
        "gildings": {},
        "id": "k7sc6yv",
        "is_submitter": false,
        "likes": null,
        "link_id": "t3_17nk88j",
        "locked": false,
        "mod_note": null,
        "mod_reason_by": null,
        "mod_reason_title": null,
        "mod_reports": [],
        "name": "t1_k7sc6yv",
        "no_follow": false,
        "num_reports": 0,
        "parent_id": "t3_17nk88j",
        "permalink": "/r/Finanzen/comments/17nk88j/ein_konto_f\u00fcr_alles/k7sc6yv/",
        "removal_reason": null,
        "replies": "",
        "report_reasons": [],
        "retrieved_on": 1699105355,
        "saved": false,
        "score": 4,
        "score_hidden": false,
        "send_replies": true,
        "stickied": false,
        "subreddit": "Finanzen",
        "subreddit_id": "t5_35m5e",
        "subreddit_name_prefixed": "r/Finanzen",
        "subreddit_type": "public",
        "top_awarded_type": null,
        "total_awards_received": 0,
        "treatment_tags": [],
        "unrepliable_reason": null,
        "updated_on": 1699105368,
        "ups": 4,
        "user_reports": [],
        "responses": []
    },
    {
        "_meta": {
            "retrieved_2nd_on": 1700302214
        },
        "all_awardings": [],
        "approved_at_utc": null,
        "approved_by": null,
        "archived": false,
        "associated_award": null,
        "author": "must_improve",
        "author_flair_background_color": null,
        "author_flair_css_class": null,
        "author_flair_richtext": [],
        "author_flair_template_id": null,
        "author_flair_text": null,
        "author_flair_text_color": null,
        "author_flair_type": "text",
        "author_fullname": "t2_15ua7n",
        "author_is_blocked": false,
        "author_patreon_flair": false,
        "author_premium": false,
        "awarders": [],
        "banned_at_utc": null,
        "banned_by": null,
        "body": "Ich bin bei der comdirect und eigentlich jahrelang zufrieden gewesen. Seit ca. 1 Jahr hab ich aber zunehmend Probleme (kostenlos) an Bargeld zu kommen. Die Deutsche Bank, die Commerzbank UND die Postbank Filiale bei mir haben zugemacht und ich krieg effektiv nur noch in der Stadtmitte Bargeld. Die n\u00e4chsten zwei Geldautomaten wurden in den vergangenen Monaten leider gesprengt.\nMittlerweile muss ich mich 20+ Minuten ins Auto setzen um kostenlos Bargeld ziehen zu k\u00f6nnen. Wtf Cash Group?\nAls Referenz, wohne in NRW, Stadt hat 170.000 Einwohner und grenzt an jeder Seite an eine andere Stadt. Trotzdem kein kostenloser GA innerhalb von 20 Minuten erreichbar, auch wenn ich die Stadtgrenze in Richtung von 2 anderen St\u00e4dten \u00fcberquere.\nBin ich mit der Erfahrung alleine?",
        "can_gild": false,
        "can_mod_post": false,
        "collapsed": false,
        "collapsed_because_crowd_control": null,
        "collapsed_reason": null,
        "collapsed_reason_code": null,
        "comment_type": null,
        "controversiality": 0,
        "created": 1699111604.0,
        "created_utc": 1699111604.0,
        "distinguished": null,
        "downs": 0,
        "edited": false,
        "gilded": 0,
        "gildings": {},
        "id": "k7sr5r8",
        "is_submitter": false,
        "likes": null,
        "link_id": "t3_17nk88j",
        "locked": false,
        "mod_note": null,
        "mod_reason_by": null,
        "mod_reason_title": null,
        "mod_reports": [],
        "name": "t1_k7sr5r8",
        "no_follow": false,
        "num_reports": 0,
        "parent_id": "t3_17nk88j",
        "permalink": "/r/Finanzen/comments/17nk88j/ein_konto_f\u00fcr_alles/k7sr5r8/",
        "removal_reason": null,
        "replies": "",
        "report_reasons": [],
        "retrieved_on": 1699111619,
        "saved": false,
        "score": 1,
        "score_hidden": false,
        "send_replies": true,
        "stickied": false,
        "subreddit": "Finanzen",
        "subreddit_id": "t5_35m5e",
        "subreddit_name_prefixed": "r/Finanzen",
        "subreddit_type": "public",
        "top_awarded_type": null,
        "total_awards_received": 0,
        "treatment_tags": [],
        "unrepliable_reason": null,
        "updated_on": 1699111634,
        "ups": 1,
        "user_reports": [],
        "responses": []
    },
    {
        "_meta": {
            "removal_type": "removed",
            "retrieved_2nd_on": 1700304769,
            "was_deleted_later": true
        },
        "all_awardings": [],
        "approved_at_utc": null,
        "approved_by": null,
        "archived": false,
        "associated_award": null,
        "author": "Longjumping_Two_7716",
        "author_flair_background_color": null,
        "author_flair_css_class": null,
        "author_flair_richtext": [],
        "author_flair_template_id": null,
        "author_flair_text": null,
        "author_flair_text_color": null,
        "author_flair_type": "text",
        "author_fullname": "t2_uez56lx4",
        "author_is_blocked": false,
        "author_patreon_flair": false,
        "author_premium": false,
        "awarders": [],
        "banned_at_utc": null,
        "banned_by": null,
        "body": "Nur ein Konto....Dann wird das Konto gesperrt weil Ali zuf\u00e4llig deine iban getippt hat und schon stehst du auf der Stra\u00dfe",
        "can_gild": false,
        "can_mod_post": false,
        "collapsed": false,
        "collapsed_because_crowd_control": null,
        "collapsed_reason": null,
        "collapsed_reason_code": null,
        "comment_type": null,
        "controversiality": 0,
        "created": 1699115126.0,
        "created_utc": 1699115126.0,
        "distinguished": null,
        "downs": 0,
        "edited": false,
        "gilded": 0,
        "gildings": {},
        "id": "k7t05ku",
        "is_submitter": false,
        "likes": null,
        "link_id": "t3_17nk88j",
        "locked": false,
        "mod_note": null,
        "mod_reason_by": null,
        "mod_reason_title": null,
        "mod_reports": [],
        "name": "t1_k7t05ku",
        "no_follow": true,
        "num_reports": 0,
        "parent_id": "t3_17nk88j",
        "permalink": "/r/Finanzen/comments/17nk88j/ein_konto_f\u00fcr_alles/k7t05ku/",
        "removal_reason": null,
        "replies": "",
        "report_reasons": [],
        "retrieved_on": 1699115142,
        "saved": false,
        "score": -4,
        "score_hidden": false,
        "send_replies": true,
        "stickied": false,
        "subreddit": "Finanzen",
        "subreddit_id": "t5_35m5e",
        "subreddit_name_prefixed": "r/Finanzen",
        "subreddit_type": "public",
        "top_awarded_type": null,
        "total_awards_received": 0,
        "treatment_tags": [],
        "unrepliable_reason": null,
        "updated_on": 1699115157,
        "ups": -4,
        "user_reports": [],
        "responses": []
    },
    {
        "_meta": {
            "removal_type": "deleted",
            "retrieved_2nd_on": 1700309580,
            "was_deleted_later": true
        },
        "all_awardings": [],
        "approved_at_utc": null,
        "approved_by": null,
        "archived": false,
        "associated_award": null,
        "author": "occio",
        "author_flair_background_color": null,
        "author_flair_css_class": null,
        "author_flair_richtext": [],
        "author_flair_template_id": null,
        "author_flair_text": null,
        "author_flair_text_color": "dark",
        "author_flair_type": "text",
        "author_fullname": "t2_3vpin",
        "author_is_blocked": false,
        "author_patreon_flair": false,
        "author_premium": false,
        "awarders": [],
        "banned_at_utc": null,
        "banned_by": null,
        "body": "[URL]\nDa will ich weder Kunde noch Mitarbeiter noch Teilhaber sein.",
        "can_gild": false,
        "can_mod_post": false,
        "collapsed": false,
        "collapsed_because_crowd_control": null,
        "collapsed_reason": null,
        "collapsed_reason_code": null,
        "comment_type": null,
        "controversiality": 0,
        "created": 1699121547.0,
        "created_utc": 1699121547.0,
        "distinguished": null,
        "downs": 0,
        "edited": false,
        "gilded": 0,
        "gildings": {},
        "id": "k7thjxi",
        "is_submitter": false,
        "likes": null,
        "link_id": "t3_17nk88j",
        "locked": false,
        "mod_note": null,
        "mod_reason_by": null,
        "mod_reason_title": null,
        "mod_reports": [],
        "name": "t1_k7thjxi",
        "no_follow": true,
        "num_reports": 0,
        "parent_id": "t3_17nk88j",
        "permalink": "/r/Finanzen/comments/17nk88j/ein_konto_f\u00fcr_alles/k7thjxi/",
        "removal_reason": null,
        "replies": "",
        "report_reasons": [],
        "retrieved_on": 1699121565,
        "saved": false,
        "score": 1,
        "score_hidden": false,
        "send_replies": true,
        "stickied": false,
        "subreddit": "Finanzen",
        "subreddit_id": "t5_35m5e",
        "subreddit_name_prefixed": "r/Finanzen",
        "subreddit_type": "public",
        "top_awarded_type": null,
        "total_awards_received": 0,
        "treatment_tags": [],
        "unrepliable_reason": null,
        "updated_on": 1699121578,
        "ups": 1,
        "user_reports": [],
        "responses": []
    },
    {
        "_meta": {
            "retrieved_2nd_on": 1700309764
        },
        "all_awardings": [],
        "approved_at_utc": null,
        "approved_by": null,
        "archived": false,
        "associated_award": null,
        "author": "occio",
        "author_flair_background_color": null,
        "author_flair_css_class": null,
        "author_flair_richtext": [],
        "author_flair_template_id": null,
        "author_flair_text": null,
        "author_flair_text_color": null,
        "author_flair_type": "text",
        "author_fullname": "t2_3vpin",
        "author_is_blocked": false,
        "author_patreon_flair": false,
        "author_premium": false,
        "awarders": [],
        "banned_at_utc": null,
        "banned_by": null,
        "body": "Guckst du hier [URL]\nBei DKB kriegst du bis auf Einzelorder kriegst du da alles g\u00fcnstig.",
        "can_gild": false,
        "can_mod_post": false,
        "collapsed": false,
        "collapsed_because_crowd_control": null,
        "collapsed_reason": null,
        "collapsed_reason_code": null,
        "comment_type": null,
        "controversiality": 0,
        "created": 1699121773.0,
        "created_utc": 1699121773.0,
        "distinguished": null,
        "downs": 0,
        "edited": false,
        "gilded": 0,
        "gildings": {},
        "id": "k7ti6ev",
        "is_submitter": false,
        "likes": null,
        "link_id": "t3_17nk88j",
        "locked": false,
        "mod_note": null,
        "mod_reason_by": null,
        "mod_reason_title": null,
        "mod_reports": [],
        "name": "t1_k7ti6ev",
        "no_follow": true,
        "num_reports": 0,
        "parent_id": "t3_17nk88j",
        "permalink": "/r/Finanzen/comments/17nk88j/ein_konto_f\u00fcr_alles/k7ti6ev/",
        "removal_reason": null,
        "replies": "",
        "report_reasons": [],
        "retrieved_on": 1699121790,
        "saved": false,
        "score": 1,
        "score_hidden": false,
        "send_replies": true,
        "stickied": false,
        "subreddit": "Finanzen",
        "subreddit_id": "t5_35m5e",
        "subreddit_name_prefixed": "r/Finanzen",
        "subreddit_type": "public",
        "top_awarded_type": null,
        "total_awards_received": 0,
        "treatment_tags": [],
        "unrepliable_reason": null,
        "updated_on": 1699121804,
        "ups": 1,
        "user_reports": [],
        "responses": []
    },
    {
        "_meta": {
            "retrieved_2nd_on": 1700315055
        },
        "all_awardings": [],
        "approved_at_utc": null,
        "approved_by": null,
        "archived": false,
        "associated_award": null,
        "author": "ArnoldVonNuehm",
        "author_flair_background_color": null,
        "author_flair_css_class": null,
        "author_flair_richtext": [],
        "author_flair_template_id": null,
        "author_flair_text": null,
        "author_flair_text_color": null,
        "author_flair_type": "text",
        "author_fullname": "t2_fg0wzc3",
        "author_is_blocked": false,
        "author_patreon_flair": false,
        "author_premium": false,
        "awarders": [],
        "banned_at_utc": null,
        "banned_by": null,
        "body": "Nur so nebenbei:\nF\u00fcr das F\u00fchren des Girokonto berechnet die Bank 4,90 Euro monatliche Geb\u00fchren. Diese Geb\u00fchr entf\u00e4llt, wenn Sie eine der folgenden Bedingungen erf\u00fcllen:\ndie ersten sechs Monate nach Er\u00f6ffnung generell geb\u00fchrenfrei\nKunde ist als Student, Azubi oder Sch\u00fcler unter 28 Jahre alt\ndas Konto weist einem monatlichen Geldeingang von min. 700 Euro auf\nder Kunde bezahlt 3 mal pro Monat \u00fcber Apple Pay oder Google Pay\nder Kunde f\u00fchrt 1 Trade/1 Wertpapiersparplanausf\u00fchrung pro Monat aus\nQuelle",
        "can_gild": false,
        "can_mod_post": false,
        "collapsed": false,
        "collapsed_because_crowd_control": null,
        "collapsed_reason": null,
        "collapsed_reason_code": null,
        "comment_type": null,
        "controversiality": 0,
        "created": 1699128346.0,
        "created_utc": 1699128346.0,
        "distinguished": null,
        "downs": 0,
        "edited": false,
        "gilded": 0,
        "gildings": {},
        "id": "k7u08c1",
        "is_submitter": false,
        "likes": null,
        "link_id": "t3_17nk88j",
        "locked": false,
        "mod_note": null,
        "mod_reason_by": null,
        "mod_reason_title": null,
        "mod_reports": [],
        "name": "t1_k7u08c1",
        "no_follow": true,
        "num_reports": 0,
        "parent_id": "t3_17nk88j",
        "permalink": "/r/Finanzen/comments/17nk88j/ein_konto_f\u00fcr_alles/k7u08c1/",
        "removal_reason": null,
        "replies": "",
        "report_reasons": [],
        "retrieved_on": 1699128363,
        "saved": false,
        "score": 1,
        "score_hidden": false,
        "send_replies": true,
        "stickied": false,
        "subreddit": "Finanzen",
        "subreddit_id": "t5_35m5e",
        "subreddit_name_prefixed": "r/Finanzen",
        "subreddit_type": "public",
        "top_awarded_type": null,
        "total_awards_received": 0,
        "treatment_tags": [],
        "unrepliable_reason": null,
        "updated_on": 1699128377,
        "ups": 1,
        "user_reports": [],
        "responses": []
    },
    {
        "_meta": {
            "retrieved_2nd_on": 1700315306
        },
        "all_awardings": [],
        "approved_at_utc": null,
        "approved_by": null,
        "archived": false,
        "associated_award": null,
        "author": "samba_pro",
        "author_flair_background_color": null,
        "author_flair_css_class": null,
        "author_flair_richtext": [],
        "author_flair_template_id": null,
        "author_flair_text": null,
        "author_flair_text_color": null,
        "author_flair_type": "text",
        "author_fullname": "t2_29tv2ovm",
        "author_is_blocked": false,
        "author_patreon_flair": false,
        "author_premium": false,
        "awarders": [],
        "banned_at_utc": null,
        "banned_by": null,
        "body": "Geht mit \u00e4hnlich mit den Automaten. Zum Gl\u00fcck gibt\u2019s aber einen Edeka die Stra\u00dfe runter, bei dem man ab 10\u20ac Einkauf kostenlos Bargeld abheben kann.",
        "can_gild": false,
        "can_mod_post": false,
        "collapsed": false,
        "collapsed_because_crowd_control": null,
        "collapsed_reason": null,
        "collapsed_reason_code": null,
        "comment_type": null,
        "controversiality": 0,
        "created": 1699128654.0,
        "created_utc": 1699128654.0,
        "distinguished": null,
        "downs": 0,
        "edited": false,
        "gilded": 0,
        "gildings": {},
        "id": "k7u12dj",
        "is_submitter": false,
        "likes": null,
        "link_id": "t3_17nk88j",
        "locked": false,
        "mod_note": null,
        "mod_reason_by": null,
        "mod_reason_title": null,
        "mod_reports": [],
        "name": "t1_k7u12dj",
        "no_follow": true,
        "num_reports": 0,
        "parent_id": "t1_k7sr5r8",
        "permalink": "/r/Finanzen/comments/17nk88j/ein_konto_f\u00fcr_alles/k7u12dj/",
        "removal_reason": null,
        "replies": "",
        "report_reasons": [],
        "retrieved_on": 1699128671,
        "saved": false,
        "score": 1,
        "score_hidden": false,
        "send_replies": true,
        "stickied": false,
        "subreddit": "Finanzen",
        "subreddit_id": "t5_35m5e",
        "subreddit_name_prefixed": "r/Finanzen",
        "subreddit_type": "public",
        "top_awarded_type": null,
        "total_awards_received": 0,
        "treatment_tags": [],
        "unrepliable_reason": null,
        "updated_on": 1699128685,
        "ups": 1,
        "user_reports": [],
        "responses": []
    },
    {
        "_meta": {
            "is_edited": true,
            "retrieved_2nd_on": 1700315980
        },
        "all_awardings": [],
        "approved_at_utc": null,
        "approved_by": null,
        "archived": false,
        "associated_award": null,
        "author": "MorbusLongus",
        "author_flair_background_color": null,
        "author_flair_css_class": null,
        "author_flair_richtext": [],
        "author_flair_template_id": null,
        "author_flair_text": null,
        "author_flair_text_color": null,
        "author_flair_type": "text",
        "author_fullname": "t2_qvm7acrh",
        "author_is_blocked": false,
        "author_patreon_flair": false,
        "author_premium": false,
        "awarders": [],
        "banned_at_utc": null,
        "banned_by": null,
        "body": "Ich bin seit einem halben Jahr bei der Comdirect und sehe das Problem nicht. Ich gehe um die Ecke zur VR oder Sparkasse und es geht.\nIch benutze aber nicht die Girocard, sondern die Visa, keine Probleme bisher.",
        "can_gild": false,
        "can_mod_post": false,
        "collapsed": false,
        "collapsed_because_crowd_control": null,
        "collapsed_reason": null,
        "collapsed_reason_code": null,
        "comment_type": null,
        "controversiality": 0,
        "created": 1699129463.0,
        "created_utc": 1699129463.0,
        "distinguished": null,
        "downs": 0,
        "edited": false,
        "gilded": 0,
        "gildings": {},
        "id": "k7u35y3",
        "is_submitter": false,
        "likes": null,
        "link_id": "t3_17nk88j",
        "locked": false,
        "mod_note": null,
        "mod_reason_by": null,
        "mod_reason_title": null,
        "mod_reports": [],
        "name": "t1_k7u35y3",
        "no_follow": true,
        "num_reports": 0,
        "parent_id": "t1_k7sr5r8",
        "permalink": "/r/Finanzen/comments/17nk88j/ein_konto_f\u00fcr_alles/k7u35y3/",
        "removal_reason": null,
        "replies": "",
        "report_reasons": [],
        "retrieved_on": 1699129482,
        "saved": false,
        "score": 2,
        "score_hidden": false,
        "send_replies": true,
        "stickied": false,
        "subreddit": "Finanzen",
        "subreddit_id": "t5_35m5e",
        "subreddit_name_prefixed": "r/Finanzen",
        "subreddit_type": "public",
        "top_awarded_type": null,
        "total_awards_received": 0,
        "treatment_tags": [],
        "unrepliable_reason": null,
        "updated_on": 1699129494,
        "ups": 2,
        "user_reports": [],
        "responses": []
    },
    {
        "_meta": {
            "retrieved_2nd_on": 1700320525
        },
        "all_awardings": [],
        "approved_at_utc": null,
        "approved_by": null,
        "archived": false,
        "associated_award": null,
        "author": "must_improve",
        "author_flair_background_color": null,
        "author_flair_css_class": null,
        "author_flair_richtext": [],
        "author_flair_template_id": null,
        "author_flair_text": null,
        "author_flair_text_color": null,
        "author_flair_type": "text",
        "author_fullname": "t2_15ua7n",
        "author_is_blocked": false,
        "author_patreon_flair": false,
        "author_premium": false,
        "awarders": [],
        "banned_at_utc": null,
        "banned_by": null,
        "body": "Kostet doch in beiden F\u00e4llen oder?",
        "can_gild": false,
        "can_mod_post": false,
        "collapsed": false,
        "collapsed_because_crowd_control": null,
        "collapsed_reason": null,
        "collapsed_reason_code": null,
        "comment_type": null,
        "controversiality": 0,
        "created": 1699135030.0,
        "created_utc": 1699135030.0,
        "distinguished": null,
        "downs": 0,
        "edited": false,
        "gilded": 0,
        "gildings": {},
        "id": "k7uhach",
        "is_submitter": false,
        "likes": null,
        "link_id": "t3_17nk88j",
        "locked": false,
        "mod_note": null,
        "mod_reason_by": null,
        "mod_reason_title": null,
        "mod_reports": [],
        "name": "t1_k7uhach",
        "no_follow": true,
        "num_reports": 0,
        "parent_id": "t1_k7u35y3",
        "permalink": "/r/Finanzen/comments/17nk88j/ein_konto_f\u00fcr_alles/k7uhach/",
        "removal_reason": null,
        "replies": "",
        "report_reasons": [],
        "retrieved_on": 1699135046,
        "saved": false,
        "score": 1,
        "score_hidden": false,
        "send_replies": true,
        "stickied": false,
        "subreddit": "Finanzen",
        "subreddit_id": "t5_35m5e",
        "subreddit_name_prefixed": "r/Finanzen",
        "subreddit_type": "public",
        "top_awarded_type": null,
        "total_awards_received": 0,
        "treatment_tags": [],
        "unrepliable_reason": null,
        "updated_on": 1699135061,
        "ups": 1,
        "user_reports": [],
        "responses": []
    },
    {
        "_meta": {
            "retrieved_2nd_on": 1700321623
        },
        "all_awardings": [],
        "approved_at_utc": null,
        "approved_by": null,
        "archived": false,
        "associated_award": null,
        "author": "MorbusLongus",
        "author_flair_background_color": null,
        "author_flair_css_class": null,
        "author_flair_richtext": [],
        "author_flair_template_id": null,
        "author_flair_text": null,
        "author_flair_text_color": null,
        "author_flair_type": "text",
        "author_fullname": "t2_qvm7acrh",
        "author_is_blocked": false,
        "author_patreon_flair": false,
        "author_premium": false,
        "awarders": [],
        "banned_at_utc": null,
        "banned_by": null,
        "body": "Hat du die Visa Debitkarte? Mit der kannst du 3x im Monat gratis bei allen Automaten mit Visa-Zeichen kostenlos abheben. Das hei\u00dft Sparkasse und VR auf jeden Fall. Die App/ die Website hat aber auch einen Automatenfinder, der sagt dir mit welcher Karte wo was geht.\nWar \u00fcbrigens der Hauptgrund, von der VR-Bank weg zu wechseln, musst mal probieren.",
        "can_gild": false,
        "can_mod_post": false,
        "collapsed": false,
        "collapsed_because_crowd_control": null,
        "collapsed_reason": null,
        "collapsed_reason_code": null,
        "comment_type": null,
        "controversiality": 0,
        "created": 1699136371.0,
        "created_utc": 1699136371.0,
        "distinguished": null,
        "downs": 0,
        "edited": false,
        "gilded": 0,
        "gildings": {},
        "id": "k7ukozq",
        "is_submitter": false,
        "likes": null,
        "link_id": "t3_17nk88j",
        "locked": false,
        "mod_note": null,
        "mod_reason_by": null,
        "mod_reason_title": null,
        "mod_reports": [],
        "name": "t1_k7ukozq",
        "no_follow": true,
        "num_reports": 0,
        "parent_id": "t1_k7uhach",
        "permalink": "/r/Finanzen/comments/17nk88j/ein_konto_f\u00fcr_alles/k7ukozq/",
        "removal_reason": null,
        "replies": "",
        "report_reasons": [],
        "retrieved_on": 1699136386,
        "saved": false,
        "score": 3,
        "score_hidden": false,
        "send_replies": true,
        "stickied": false,
        "subreddit": "Finanzen",
        "subreddit_id": "t5_35m5e",
        "subreddit_name_prefixed": "r/Finanzen",
        "subreddit_type": "public",
        "top_awarded_type": null,
        "total_awards_received": 0,
        "treatment_tags": [],
        "unrepliable_reason": null,
        "updated_on": 1699211401,
        "ups": 3,
        "user_reports": [],
        "responses": []
    },
    {
        "_meta": {
            "retrieved_2nd_on": 1700332482
        },
        "all_awardings": [],
        "approved_at_utc": null,
        "approved_by": null,
        "archived": false,
        "associated_award": null,
        "author": "Different-Pain-3629",
        "author_flair_background_color": null,
        "author_flair_css_class": null,
        "author_flair_richtext": [],
        "author_flair_template_id": null,
        "author_flair_text": null,
        "author_flair_text_color": null,
        "author_flair_type": "text",
        "author_fullname": "t2_8whz6qtb",
        "author_is_blocked": false,
        "author_patreon_flair": false,
        "author_premium": false,
        "awarders": [],
        "banned_at_utc": null,
        "banned_by": null,
        "body": "Wir sind auch bei der ING Diba und dort dann Sparbrief statt Tagesgeld - aufm Tagesgeld liegt nur das N\u00f6tigste, das man zwischendurch mal f\u00fcr Notf\u00e4lle braucht.",
        "can_gild": false,
        "can_mod_post": false,
        "collapsed": false,
        "collapsed_because_crowd_control": null,
        "collapsed_reason": null,
        "collapsed_reason_code": null,
        "comment_type": null,
        "controversiality": 0,
        "created": 1699151318.0,
        "created_utc": 1699151318.0,
        "distinguished": null,
        "downs": 0,
        "edited": false,
        "gilded": 0,
        "gildings": {},
        "id": "k7vkqa7",
        "is_submitter": false,
        "likes": null,
        "link_id": "t3_17nk88j",
        "locked": false,
        "mod_note": null,
        "mod_reason_by": null,
        "mod_reason_title": null,
        "mod_reports": [],
        "name": "t1_k7vkqa7",
        "no_follow": true,
        "num_reports": 0,
        "parent_id": "t1_k7s2btm",
        "permalink": "/r/Finanzen/comments/17nk88j/ein_konto_f\u00fcr_alles/k7vkqa7/",
        "removal_reason": null,
        "replies": "",
        "report_reasons": [],
        "retrieved_on": 1699151335,
        "saved": false,
        "score": 1,
        "score_hidden": false,
        "send_replies": true,
        "stickied": false,
        "subreddit": "Finanzen",
        "subreddit_id": "t5_35m5e",
        "subreddit_name_prefixed": "r/Finanzen",
        "subreddit_type": "public",
        "top_awarded_type": null,
        "total_awards_received": 0,
        "treatment_tags": [],
        "unrepliable_reason": null,
        "updated_on": 1699213887,
        "ups": 1,
        "user_reports": [],
        "responses": []
    },
    {
        "_meta": {
            "retrieved_2nd_on": 1699302568
        },
        "all_awardings": [],
        "approved_at_utc": null,
        "approved_by": null,
        "archived": false,
        "associated_award": null,
        "author": "javapersist",
        "author_flair_background_color": null,
        "author_flair_css_class": null,
        "author_flair_richtext": [],
        "author_flair_template_id": null,
        "author_flair_text": null,
        "author_flair_text_color": null,
        "author_flair_type": "text",
        "author_fullname": "t2_xamdj",
        "author_is_blocked": false,
        "author_patreon_flair": false,
        "author_premium": false,
        "awarders": [],
        "banned_at_utc": null,
        "banned_by": null,
        "body": "This, wollte das auch grad schreiben.  \nHabe jetzt nicht nachgeprueft, wuerde aber annehmen, dass die meisten  \neine Debitkarte anbieten, mit der man kostenlos abheben kann.",
        "can_gild": false,
        "can_mod_post": false,
        "collapsed": false,
        "collapsed_because_crowd_control": null,
        "collapsed_reason": null,
        "collapsed_reason_code": null,
        "comment_type": null,
        "controversiality": 0,
        "created": 1699172960.0,
        "created_utc": 1699172960.0,
        "distinguished": null,
        "downs": 0,
        "edited": false,
        "gilded": 0,
        "gildings": {},
        "id": "k7wipfv",
        "is_submitter": false,
        "likes": null,
        "link_id": "t3_17nk88j",
        "locked": false,
        "mod_note": null,
        "mod_reason_by": null,
        "mod_reason_title": null,
        "mod_reports": [],
        "name": "t1_k7wipfv",
        "no_follow": false,
        "num_reports": 0,
        "parent_id": "t1_k7ukozq",
        "permalink": "/r/Finanzen/comments/17nk88j/ein_konto_f\u00fcr_alles/k7wipfv/",
        "removal_reason": null,
        "replies": "",
        "report_reasons": [],
        "retrieved_on": 1699172973,
        "saved": false,
        "score": 1,
        "score_hidden": false,
        "send_replies": true,
        "stickied": false,
        "subreddit": "Finanzen",
        "subreddit_id": "t5_35m5e",
        "subreddit_name_prefixed": "r/Finanzen",
        "subreddit_type": "public",
        "top_awarded_type": null,
        "total_awards_received": 0,
        "treatment_tags": [],
        "unrepliable_reason": null,
        "updated_on": 1699216195,
        "ups": 1,
        "user_reports": [],
        "responses": []
    },
    {
        "_meta": {
            "retrieved_2nd_on": 1700359773
        },
        "all_awardings": [],
        "approved_at_utc": null,
        "approved_by": null,
        "archived": false,
        "associated_award": null,
        "author": "fsw",
        "author_flair_background_color": null,
        "author_flair_css_class": null,
        "author_flair_richtext": [],
        "author_flair_template_id": null,
        "author_flair_text": null,
        "author_flair_text_color": null,
        "author_flair_type": "text",
        "author_fullname": "t2_883re",
        "author_is_blocked": false,
        "author_patreon_flair": false,
        "author_premium": false,
        "awarders": [],
        "banned_at_utc": null,
        "banned_by": null,
        "body": "Bei comdirect kannst du mit Barzahlung/viacash bei fast jedem Rossmann, Rewe, Penny oder dm Geld an der Kasse holen, auch ohne was einzukaufen. Au\u00dferdem kann man mit einer der Karten dreimal pro Monat kostenlos Geld abheben bei den meisten Geldautomaten.",
        "can_gild": false,
        "can_mod_post": false,
        "collapsed": false,
        "collapsed_because_crowd_control": null,
        "collapsed_reason": null,
        "collapsed_reason_code": null,
        "comment_type": null,
        "controversiality": 0,
        "created": 1699206831.0,
        "created_utc": 1699206831.0,
        "distinguished": null,
        "downs": 0,
        "edited": false,
        "gilded": 0,
        "gildings": {},
        "id": "k7yeqfe",
        "is_submitter": false,
        "likes": null,
        "link_id": "t3_17nk88j",
        "locked": false,
        "mod_note": null,
        "mod_reason_by": null,
        "mod_reason_title": null,
        "mod_reports": [],
        "name": "t1_k7yeqfe",
        "no_follow": true,
        "num_reports": 0,
        "parent_id": "t1_k7sr5r8",
        "permalink": "/r/Finanzen/comments/17nk88j/ein_konto_f\u00fcr_alles/k7yeqfe/",
        "removal_reason": null,
        "replies": "",
        "report_reasons": [],
        "retrieved_on": 1699206846,
        "saved": false,
        "score": 1,
        "score_hidden": false,
        "send_replies": true,
        "stickied": false,
        "subreddit": "Finanzen",
        "subreddit_id": "t5_35m5e",
        "subreddit_name_prefixed": "r/Finanzen",
        "subreddit_type": "public",
        "top_awarded_type": null,
        "total_awards_received": 0,
        "treatment_tags": [],
        "unrepliable_reason": null,
        "updated_on": 1699220855,
        "ups": 1,
        "user_reports": [],
        "responses": []
    },
    {
        "_meta": {
            "retrieved_2nd_on": 1700359847
        },
        "all_awardings": [],
        "approved_at_utc": null,
        "approved_by": null,
        "archived": false,
        "associated_award": null,
        "author": "must_improve",
        "author_flair_background_color": null,
        "author_flair_css_class": null,
        "author_flair_richtext": [],
        "author_flair_template_id": null,
        "author_flair_text": null,
        "author_flair_text_color": null,
        "author_flair_type": "text",
        "author_fullname": "t2_15ua7n",
        "author_is_blocked": false,
        "author_patreon_flair": false,
        "author_premium": false,
        "awarders": [],
        "banned_at_utc": null,
        "banned_by": null,
        "body": "Interessant, danke!\nFinde es zwar bl\u00f6d dass ich dann zus\u00e4tzlich zur girocard noch ne weitere Karte rumschleppe aber der Tipp ist sehr gut.",
        "can_gild": false,
        "can_mod_post": false,
        "collapsed": false,
        "collapsed_because_crowd_control": null,
        "collapsed_reason": null,
        "collapsed_reason_code": null,
        "comment_type": null,
        "controversiality": 0,
        "created": 1699206927.0,
        "created_utc": 1699206927.0,
        "distinguished": null,
        "downs": 0,
        "edited": false,
        "gilded": 0,
        "gildings": {},
        "id": "k7yezym",
        "is_submitter": false,
        "likes": null,
        "link_id": "t3_17nk88j",
        "locked": false,
        "mod_note": null,
        "mod_reason_by": null,
        "mod_reason_title": null,
        "mod_reports": [],
        "name": "t1_k7yezym",
        "no_follow": true,
        "num_reports": 0,
        "parent_id": "t1_k7wipfv",
        "permalink": "/r/Finanzen/comments/17nk88j/ein_konto_f\u00fcr_alles/k7yezym/",
        "removal_reason": null,
        "replies": "",
        "report_reasons": [],
        "retrieved_on": 1699206943,
        "saved": false,
        "score": 1,
        "score_hidden": false,
        "send_replies": true,
        "stickied": false,
        "subreddit": "Finanzen",
        "subreddit_id": "t5_35m5e",
        "subreddit_name_prefixed": "r/Finanzen",
        "subreddit_type": "public",
        "top_awarded_type": null,
        "total_awards_received": 0,
        "treatment_tags": [],
        "unrepliable_reason": null,
        "updated_on": 1699220872,
        "ups": 1,
        "user_reports": [],
        "responses": []
    },
    {
        "_meta": {
            "retrieved_2nd_on": 1700375783
        },
        "all_awardings": [],
        "approved_at_utc": null,
        "approved_by": null,
        "archived": false,
        "associated_award": null,
        "author": "seba07",
        "author_flair_background_color": null,
        "author_flair_css_class": null,
        "author_flair_richtext": [],
        "author_flair_template_id": null,
        "author_flair_text": null,
        "author_flair_text_color": null,
        "author_flair_type": "text",
        "author_fullname": "t2_bm7u5ew",
        "author_is_blocked": false,
        "author_patreon_flair": false,
        "author_premium": false,
        "awarders": [],
        "banned_at_utc": null,
        "banned_by": null,
        "body": "Kann man bei dir nicht im Supermarkt beim Einkaufen Geld abheben? Das finde ich super komfortabel, nachdem man da ja eh regelm\u00e4\u00dfig ist. Extra zu einer Bank oder Geldautomaten gehen braucht man dann gar nicht mehr.",
        "can_gild": false,
        "can_mod_post": false,
        "collapsed": false,
        "collapsed_because_crowd_control": null,
        "collapsed_reason": null,
        "collapsed_reason_code": null,
        "comment_type": null,
        "controversiality": 0,
        "created": 1699225183.0,
        "created_utc": 1699225183.0,
        "distinguished": null,
        "downs": 0,
        "edited": false,
        "gilded": 0,
        "gildings": {},
        "id": "k7zth4r",
        "is_submitter": false,
        "likes": null,
        "link_id": "t3_17nk88j",
        "locked": false,
        "mod_note": null,
        "mod_reason_by": null,
        "mod_reason_title": null,
        "mod_reports": [],
        "name": "t1_k7zth4r",
        "no_follow": true,
        "num_reports": 0,
        "parent_id": "t1_k7sr5r8",
        "permalink": "/r/Finanzen/comments/17nk88j/ein_konto_f\u00fcr_alles/k7zth4r/",
        "removal_reason": null,
        "replies": "",
        "report_reasons": [],
        "retrieved_on": 1699225197,
        "saved": false,
        "score": 1,
        "score_hidden": false,
        "send_replies": true,
        "stickied": false,
        "subreddit": "Finanzen",
        "subreddit_id": "t5_35m5e",
        "subreddit_name_prefixed": "r/Finanzen",
        "subreddit_type": "public",
        "top_awarded_type": null,
        "total_awards_received": 0,
        "treatment_tags": [],
        "unrepliable_reason": null,
        "updated_on": 1699225882,
        "ups": 1,
        "user_reports": [],
        "responses": []
    }
]